{
 "an_data_depute": {
  "dateNais": "1957-12-17",
  "femme": true,
  "ident": {
   "alpha": "DuboisM",
   "civ": "Mme",
   "nom": "Dubois",
   "prenom": "Marianne",
   "trigramme": "MDB"
  },
  "nom": "Marianne Dubois"
 },
 "an_www_depute": {
  "groupe": "Les Républicains",
  "imgurl": "https://www2.assemblee-nationale.fr/static/tribun/15/photos/342935.jpg",
  "nosiege": "20"
 },
 "an_www_pic": {},
 "an_www_social": {
  "facebook_link": "https://fr-fr.facebook.com/DuboisMarianne/",
  "twitter_link": "https://twitter.com/@DuboisMarianne/"
 },
 "circo": {
  "acteurId": "OMC_PA342935",
  "civ": "Mme",
  "communes": [
   "Andonville (45480)",
   "Aschères-le-Marché (45170)",
   "Ascoux (45300)",
   "Attray (45170)",
   "Audeville (45300)",
   "Augerville-la-Rivière (45330)",
   "Aulnay-la-Rivière (45390)",
   "Autruy-sur-Juine (45480)",
   "Auvilliers-en-Gâtinais (45270)",
   "Auxy (Loiret) (45340)",
   "Barville-en-Gâtinais (45340)",
   "Batilly-en-Gâtinais (45340)",
   "Bazoches-les-Gallerandes (45480)",
   "Beauchamps-sur-Huillard (45270)",
   "Beaune-la-Rolande (45340)",
   "Bellegarde (Loiret) (45270)",
   "Boiscommun (45340)",
   "Boisseaux (45480)",
   "Bondaroy (45300)",
   "Bordeaux-en-Gâtinais (45340)",
   "Bougy-lez-Neuville (45170)",
   "Bouilly-en-Gâtinais (45300)",
   "Bouzonville-aux-Bois (45300)",
   "Boynes (45300)",
   "Boësses (45390)",
   "Briarres-sur-Essonne (45390)",
   "Bromeilles (45390)",
   "Chambon-la-Forêt (45340)",
   "Chanteau (45400)",
   "Chapelon (45270)",
   "Charmont-en-Beauce (45480)",
   "Chaussy (Loiret) (45480)",
   "Chilleurs-aux-Bois (45170)",
   "Châtillon-le-Roi (45480)",
   "Courcelles (Loiret) (45300)",
   "Courcy-aux-Loges (45300)",
   "Crottes-en-Pithiverais (45170)",
   "Césarville-Dossainville (45300)",
   "Dadonville (45300)",
   "Desmont (45390)",
   "Dimancheville (45390)",
   "Echilleuses (45390)",
   "Egry (45340)",
   "Engenville (45300)",
   "Erceville (45480)",
   "Escrennes (45300)",
   "Estouy (45300)",
   "Fleury-les-Aubrais (45400)",
   "Fréville-du-Gâtinais (45270)",
   "Gaubertin (45340)",
   "Givraines (45300)",
   "Grangermont (45390)",
   "Greneville-en-Beauce (45480)",
   "Guigneville (45300)",
   "Ingrannes (45450)",
   "Intville-la-Guétard (45300)",
   "Jouy-en-Pithiverais (45480)",
   "Juranville (45340)",
   "La Neuville-sur-Essonne (45390)",
   "Laas (Loiret) (45300)",
   "Ladon (45270)",
   "Le Malesherbois (45300)",
   "Le Malesherbois (45330)",
   "Lorcy (45490)",
   "Loury (45470)",
   "Léouville (45480)",
   "Mareau-aux-Bois (45300)",
   "Marsainvilliers (45300)",
   "Montbarrois (45340)",
   "Montigny (Loiret) (45170)",
   "Montliard (45340)",
   "Morville-en-Beauce (45300)",
   "Moulon (Loiret) (45270)",
   "Mézières-en-Gâtinais (45270)",
   "Nancray-sur-Rimarde (45340)",
   "Nesploy (45270)",
   "Neuville-aux-Bois (45170)",
   "Nibelle (45340)",
   "Oison (45170)",
   "Ondreville-sur-Essonne (45390)",
   "Orville (Loiret) (45390)",
   "Outarville (45480)",
   "Ouzouer-sous-Bellegarde (45270)",
   "Pannecières (45300)",
   "Pithiviers (45300)",
   "Pithiviers-le-Vieil (45300)",
   "Puiseaux (45390)",
   "Quiers-sur-Bézonde (45270)",
   "Ramoulu (45300)",
   "Rebréchien (45470)",
   "Rouvres-Saint-Jean (45300)",
   "Saint-Loup-des-Vignes (45340)",
   "Saint-Lyé-la-Forêt (45170)",
   "Saint-Michel (Loiret) (45340)",
   "Santeau (45170)",
   "Sermaises (45300)",
   "Sully-la-Chapelle (45450)",
   "Thignonville (45300)",
   "Tivernon (45170)",
   "Traînou (45470)",
   "Vennecy (45760)",
   "Villemoutiers (45270)",
   "Villereau (Loiret) (45170)",
   "Vrigny (Loiret) (45300)",
   "Yèvre-la-Ville (45300)"
  ],
  "departement": "Loiret",
  "group": "Les Républicains",
  "nom": "Dubois",
  "numCirco": "5",
  "numDepartement": "45",
  "prenom": "Marianne"
 },
 "datan": "https://datan.fr/deputes/loiret-45/depute_marianne-dubois",
 "lcdg": {
  "siege": {
   "curAngleIndex": 3,
   "curRadiusIndex": 5,
   "id": "ai3ri5",
   "no": 20,
   "polar": {
    "angle": 0.20052719065466765,
    "radius": 0.625
   },
   "pos": {
    "x": 0.6124760656478668,
    "y": -0.12451585376734223
   }
  }
 },
 "nd_twitter": {
  "twitter": "DuboisMarianne",
  "url_an": "http://www2.assemblee-nationale.fr/deputes/fiche/OMC_PA342935"
 },
 "nosdeputes_link": "https://www.nosdeputes.fr/Marianne-Dubois",
 "official_link": "https://www2.assemblee-nationale.fr/deputes/fiche/OMC_PA342935",
 "scrutins": {
  "VTANR5L15V1": "A",
  "VTANR5L15V10": "C",
  "VTANR5L15V1000": "C",
  "VTANR5L15V1001": "P",
  "VTANR5L15V1002": "P",
  "VTANR5L15V1003": "P",
  "VTANR5L15V101": "C",
  "VTANR5L15V102": "C",
  "VTANR5L15V103": "P",
  "VTANR5L15V104": "A",
  "VTANR5L15V106": "P",
  "VTANR5L15V107": "P",
  "VTANR5L15V1114": "P",
  "VTANR5L15V1169": "P",
  "VTANR5L15V1170": "P",
  "VTANR5L15V1171": "P",
  "VTANR5L15V1181": "C",
  "VTANR5L15V119": "A",
  "VTANR5L15V1209": "A",
  "VTANR5L15V1216": "C",
  "VTANR5L15V1263": "C",
  "VTANR5L15V1330": "C",
  "VTANR5L15V138": "C",
  "VTANR5L15V139": "C",
  "VTANR5L15V1429": "C",
  "VTANR5L15V1432": "C",
  "VTANR5L15V1536": "C",
  "VTANR5L15V1633": "C",
  "VTANR5L15V1634": "C",
  "VTANR5L15V1662": "P",
  "VTANR5L15V1709": "C",
  "VTANR5L15V1711": "C",
  "VTANR5L15V1725": "P",
  "VTANR5L15V1726": "P",
  "VTANR5L15V1814": "C",
  "VTANR5L15V183": "C",
  "VTANR5L15V184": "C",
  "VTANR5L15V1840": "C",
  "VTANR5L15V1851": "P",
  "VTANR5L15V1852": "P",
  "VTANR5L15V1853": "P",
  "VTANR5L15V1912": "A",
  "VTANR5L15V1923": "C",
  "VTANR5L15V1941": "C",
  "VTANR5L15V1957": "A",
  "VTANR5L15V1988": "P",
  "VTANR5L15V2039": "P",
  "VTANR5L15V2059": "C",
  "VTANR5L15V2071": "C",
  "VTANR5L15V2078": "P",
  "VTANR5L15V2079": "P",
  "VTANR5L15V208": "C",
  "VTANR5L15V209": "P",
  "VTANR5L15V210": "P",
  "VTANR5L15V211": "P",
  "VTANR5L15V2130": "P",
  "VTANR5L15V2131": "P",
  "VTANR5L15V2139": "P",
  "VTANR5L15V2140": "P",
  "VTANR5L15V2146": "C",
  "VTANR5L15V2147": "P",
  "VTANR5L15V2171": "P",
  "VTANR5L15V2172": "P",
  "VTANR5L15V2173": "P",
  "VTANR5L15V2177": "C",
  "VTANR5L15V2235": "C",
  "VTANR5L15V2239": "P",
  "VTANR5L15V2241": "P",
  "VTANR5L15V2242": "A",
  "VTANR5L15V2307": "C",
  "VTANR5L15V2308": "C",
  "VTANR5L15V2329": "A",
  "VTANR5L15V2337": "C",
  "VTANR5L15V2470": "C",
  "VTANR5L15V2471": "A",
  "VTANR5L15V2472": "C",
  "VTANR5L15V2473": "A",
  "VTANR5L15V2474": "C",
  "VTANR5L15V2475": "P",
  "VTANR5L15V2476": "P",
  "VTANR5L15V2480": "P",
  "VTANR5L15V2486": "A",
  "VTANR5L15V2487": "P",
  "VTANR5L15V2489": "A",
  "VTANR5L15V2490": "A",
  "VTANR5L15V2491": "P",
  "VTANR5L15V2492": "P",
  "VTANR5L15V2509": "P",
  "VTANR5L15V2510": "P",
  "VTANR5L15V2512": "A",
  "VTANR5L15V2513": "P",
  "VTANR5L15V2514": "A",
  "VTANR5L15V2515": "A",
  "VTANR5L15V2516": "A",
  "VTANR5L15V2517": "A",
  "VTANR5L15V2518": "A",
  "VTANR5L15V2519": "A",
  "VTANR5L15V2520": "A",
  "VTANR5L15V2521": "A",
  "VTANR5L15V2522": "P",
  "VTANR5L15V2532": "A",
  "VTANR5L15V2533": "P",
  "VTANR5L15V2534": "A",
  "VTANR5L15V2535": "P",
  "VTANR5L15V2536": "A",
  "VTANR5L15V2537": "A",
  "VTANR5L15V2538": "A",
  "VTANR5L15V2543": "A",
  "VTANR5L15V2544": "A",
  "VTANR5L15V2545": "A",
  "VTANR5L15V2546": "A",
  "VTANR5L15V2547": "A",
  "VTANR5L15V2548": "A",
  "VTANR5L15V2549": "A",
  "VTANR5L15V2550": "A",
  "VTANR5L15V2551": "A",
  "VTANR5L15V2552": "A",
  "VTANR5L15V2553": "A",
  "VTANR5L15V2565": "P",
  "VTANR5L15V2566": "C",
  "VTANR5L15V2567": "C",
  "VTANR5L15V2568": "A",
  "VTANR5L15V2569": "A",
  "VTANR5L15V2570": "A",
  "VTANR5L15V2571": "A",
  "VTANR5L15V2572": "A",
  "VTANR5L15V2573": "A",
  "VTANR5L15V2574": "A",
  "VTANR5L15V2575": "P",
  "VTANR5L15V2576": "P",
  "VTANR5L15V2639": "P",
  "VTANR5L15V2640": "P",
  "VTANR5L15V2641": "C",
  "VTANR5L15V2649": "C",
  "VTANR5L15V2650": "P",
  "VTANR5L15V2706": "P",
  "VTANR5L15V272": "C",
  "VTANR5L15V2733": "P",
  "VTANR5L15V2734": "P",
  "VTANR5L15V2735": "P",
  "VTANR5L15V2736": "P",
  "VTANR5L15V2737": "P",
  "VTANR5L15V2738": "P",
  "VTANR5L15V2739": "A",
  "VTANR5L15V2740": "C",
  "VTANR5L15V2741": "P",
  "VTANR5L15V2742": "C",
  "VTANR5L15V2743": "C",
  "VTANR5L15V2744": "P",
  "VTANR5L15V2745": "P",
  "VTANR5L15V2746": "C",
  "VTANR5L15V2747": "P",
  "VTANR5L15V2748": "P",
  "VTANR5L15V2749": "A",
  "VTANR5L15V2750": "C",
  "VTANR5L15V2751": "C",
  "VTANR5L15V2752": "C",
  "VTANR5L15V2753": "P",
  "VTANR5L15V2754": "C",
  "VTANR5L15V2755": "A",
  "VTANR5L15V2756": "A",
  "VTANR5L15V2757": "P",
  "VTANR5L15V2758": "C",
  "VTANR5L15V2759": "P",
  "VTANR5L15V2760": "C",
  "VTANR5L15V2761": "C",
  "VTANR5L15V2762": "C",
  "VTANR5L15V2814": "C",
  "VTANR5L15V2816": "A",
  "VTANR5L15V2933": "C",
  "VTANR5L15V2934": "C",
  "VTANR5L15V2935": "C",
  "VTANR5L15V2936": "C",
  "VTANR5L15V2937": "C",
  "VTANR5L15V2938": "P",
  "VTANR5L15V2939": "C",
  "VTANR5L15V2947": "P",
  "VTANR5L15V2948": "C",
  "VTANR5L15V2949": "C",
  "VTANR5L15V2950": "C",
  "VTANR5L15V2951": "P",
  "VTANR5L15V2952": "C",
  "VTANR5L15V2991": "C",
  "VTANR5L15V3059": "C",
  "VTANR5L15V3076": "P",
  "VTANR5L15V3086": "A",
  "VTANR5L15V3087": "A",
  "VTANR5L15V3095": "P",
  "VTANR5L15V3096": "P",
  "VTANR5L15V3097": "P",
  "VTANR5L15V3098": "P",
  "VTANR5L15V3099": "P",
  "VTANR5L15V3100": "P",
  "VTANR5L15V3101": "P",
  "VTANR5L15V3102": "P",
  "VTANR5L15V3104": "P",
  "VTANR5L15V3106": "P",
  "VTANR5L15V3107": "P",
  "VTANR5L15V3108": "P",
  "VTANR5L15V3112": "C",
  "VTANR5L15V314": "P",
  "VTANR5L15V3186": "C",
  "VTANR5L15V3249": "A",
  "VTANR5L15V3250": "A",
  "VTANR5L15V3251": "C",
  "VTANR5L15V3254": "P",
  "VTANR5L15V3280": "P",
  "VTANR5L15V3283": "P",
  "VTANR5L15V3295": "C",
  "VTANR5L15V3308": "C",
  "VTANR5L15V3378": "C",
  "VTANR5L15V3421": "C",
  "VTANR5L15V3422": "P",
  "VTANR5L15V345": "C",
  "VTANR5L15V3454": "P",
  "VTANR5L15V3484": "A",
  "VTANR5L15V351": "C",
  "VTANR5L15V365": "A",
  "VTANR5L15V389": "P",
  "VTANR5L15V407": "C",
  "VTANR5L15V419": "P",
  "VTANR5L15V420": "P",
  "VTANR5L15V424": "P",
  "VTANR5L15V425": "A",
  "VTANR5L15V426": "P",
  "VTANR5L15V427": "P",
  "VTANR5L15V428": "P",
  "VTANR5L15V429": "A",
  "VTANR5L15V430": "P",
  "VTANR5L15V431": "A",
  "VTANR5L15V432": "A",
  "VTANR5L15V433": "A",
  "VTANR5L15V440": "C",
  "VTANR5L15V441": "C",
  "VTANR5L15V476": "P",
  "VTANR5L15V477": "P",
  "VTANR5L15V479": "C",
  "VTANR5L15V480": "C",
  "VTANR5L15V481": "C",
  "VTANR5L15V483": "C",
  "VTANR5L15V54": "C",
  "VTANR5L15V578": "C",
  "VTANR5L15V587": "P",
  "VTANR5L15V588": "P",
  "VTANR5L15V589": "P",
  "VTANR5L15V590": "P",
  "VTANR5L15V591": "P",
  "VTANR5L15V592": "P",
  "VTANR5L15V593": "P",
  "VTANR5L15V61": "P",
  "VTANR5L15V62": "P",
  "VTANR5L15V63": "C",
  "VTANR5L15V65": "P",
  "VTANR5L15V66": "P",
  "VTANR5L15V67": "P",
  "VTANR5L15V719": "P",
  "VTANR5L15V720": "C",
  "VTANR5L15V721": "A",
  "VTANR5L15V729": "A",
  "VTANR5L15V80": "P",
  "VTANR5L15V81": "P",
  "VTANR5L15V82": "C",
  "VTANR5L15V84": "P",
  "VTANR5L15V85": "P",
  "VTANR5L15V86": "C",
  "VTANR5L15V87": "C",
  "VTANR5L15V88": "C",
  "VTANR5L15V89": "A",
  "VTANR5L15V9": "C",
  "VTANR5L15V90": "A",
  "VTANR5L15V91": "A",
  "VTANR5L15V92": "P",
  "VTANR5L15V928": "C",
  "VTANR5L15V929": "A",
  "VTANR5L15V93": "P",
  "VTANR5L15V930": "P",
  "VTANR5L15V931": "P",
  "VTANR5L15V94": "C",
  "VTANR5L15V942": "P",
  "VTANR5L15V95": "P",
  "VTANR5L15V96": "C",
  "VTANR5L15V97": "C",
  "VTANR5L15V974": "C",
  "VTANR5L15V982": "C"
 },
 "twitter": {
  "id": "459093089",
  "name": "Marianne Dubois",
  "public_metrics": {
   "followers_count": 8462,
   "following_count": 4269,
   "listed_count": 182,
   "tweet_count": 3591
  },
  "username": "duboismarianne"
 },
 "twitter_username": {
  "status": "found",
  "value": "duboismarianne"
 },
 "uid": "PA342935"
}