{
 "an_data_depute": {
  "dateNais": "1952-06-16",
  "femme": true,
  "ident": {
   "alpha": "Biemouret",
   "civ": "Mme",
   "nom": "Biémouret",
   "prenom": "Gisèle",
   "trigramme": "GBE"
  },
  "nom": "Gisèle Biémouret"
 },
 "an_www_depute": {
  "groupe": "Socialistes et apparentés",
  "imgurl": "https://www2.assemblee-nationale.fr/static/tribun/15/photos/508.jpg",
  "nosiege": "515"
 },
 "an_www_pic": {},
 "an_www_social": {},
 "circo": {
  "acteurId": "OMC_PA508",
  "civ": "Mme",
  "communes": [
   "Ansan (32270)",
   "Antras (Gers) (32360)",
   "Ardizas (32430)",
   "Aubiet (32270)",
   "Auradé (32600)",
   "Avensac (32120)",
   "Avezan (32380)",
   "Ayguetinte (32410)",
   "Ayzieu (32800)",
   "Bajonnette (32120)",
   "Bascous (32190)",
   "Bazian (32320)",
   "Beaucaire (Gers) (32410)",
   "Beaumont (Gers) (32100)",
   "Beaupuy (Gers) (32600)",
   "Belmont (Gers) (32190)",
   "Berrac (32480)",
   "Bezolles (32310)",
   "Biran (32350)",
   "Bivès (32380)",
   "Blanquefort (Gers) (32270)",
   "Blaziert (32100)",
   "Bonas (32410)",
   "Bretagne-d'Armagnac (32800)",
   "Brugnens (32500)",
   "Béraut (32100)",
   "Cadeilhan (32380)",
   "Caillavet (32190)",
   "Callian (Gers) (32190)",
   "Campagne-d'Armagnac (32800)",
   "Cassaigne (32100)",
   "Castelnau-d'Arbieu (32500)",
   "Castelnau-d'Auzan Labarrère (32250)",
   "Castelnau-d'Auzan Labarrère (32440)",
   "Castelnau-sur-l'Auvignon (32100)",
   "Castet-Arrouy (32340)",
   "Castex-d'Armagnac (32240)",
   "Castillon-Debats (32190)",
   "Castillon-Massas (32360)",
   "Castillon-Savès (32490)",
   "Castéra-Lectourois (32700)",
   "Castéra-Verduzan (32410)",
   "Castéron (32380)",
   "Catonvielle (32200)",
   "Caussens (32100)",
   "Cazaubon (32150)",
   "Cazaux-d'Anglès (32190)",
   "Cazeneuve (32800)",
   "Clermont-Savès (32600)",
   "Cologne (32430)",
   "Condom (32100)",
   "Courrensan (32330)",
   "Céran (32500)",
   "Cézan (32410)",
   "Dému (32190)",
   "Eauze (32800)",
   "Encausse (32430)",
   "Endoufielle (32600)",
   "Escorneboeuf (32200)",
   "Estang (32240)",
   "Estramiac (32380)",
   "Flamarens (32340)",
   "Fleurance (32500)",
   "Fourcès (32250)",
   "Frégouville (32490)",
   "Gaudonville (32380)",
   "Gavarret-sur-Aulouste (32390)",
   "Gazaupouy (32480)",
   "Gimbrède (32340)",
   "Gimont (32200)",
   "Giscaro (32200)",
   "Gondrin (32330)",
   "Goutz (32500)",
   "Homps (Gers) (32120)",
   "Jegun (32360)",
   "Juilles (32200)",
   "Justian (32190)",
   "L'Isle-Arné (32270)",
   "L'Isle-Bouzon (32380)",
   "L'Isle-Jourdain (Gers) (32600)",
   "La Romieu (32480)",
   "La Sauvetat (Gers) (32500)",
   "Labrihe (32120)",
   "Lagarde (Gers) (32700)",
   "Lagardère (32310)",
   "Lagraulet-du-Gers (32330)",
   "Lalanne (Gers) (32500)",
   "Lamothe-Goas (32500)",
   "Lannemaignan (32240)",
   "Lannepax (32190)",
   "Larressingle (32100)",
   "Larroque-Engalin (32480)",
   "Larroque-Saint-Sernin (32410)",
   "Larroque-sur-l'Osse (32100)",
   "Larée (32150)",
   "Lauraët (32330)",
   "Lavardens (32360)",
   "Lectoure (32700)",
   "Lias (32600)",
   "Lias-d'Armagnac (32240)",
   "Ligardes (32480)",
   "Lussan (Gers) (32270)",
   "Magnas (32380)",
   "Maignaut-Tauzia (32310)",
   "Mansempuy (32120)",
   "Mansencôme (32310)",
   "Marambat (32190)",
   "Maravat (32120)",
   "Marestaing (32490)",
   "Marguestau (32150)",
   "Marsan (32270)",
   "Marsolan (32700)",
   "Mas-d'Auvignon (32700)",
   "Mauléon-d'Armagnac (32240)",
   "Maupas (Gers) (32240)",
   "Maurens (Gers) (32200)",
   "Mauroux (Gers) (32380)",
   "Mauvezin (Gers) (32120)",
   "Miradoux (32340)",
   "Miramont-Latour (32390)",
   "Mirannes (32350)",
   "Monbrun (32600)",
   "Monclar-d'Armagnac (32150)",
   "Monferran-Savès (32490)",
   "Monfort (32120)",
   "Montestruc-sur-Gers (32390)",
   "Montiron (32200)",
   "Montréal (Gers) (32250)",
   "Mouchan (32330)",
   "Mourède (32190)",
   "Mérens (32360)",
   "Noulens (32800)",
   "Ordan-Larroque (32350)",
   "Panjas (32110)",
   "Pauilhac (32500)",
   "Pergain-Taillac (32700)",
   "Pessoulens (32380)",
   "Peyrecave (32340)",
   "Peyrusse-Massas (32360)",
   "Pis (32500)",
   "Plieux (32340)",
   "Pouy-Roquelaure (32480)",
   "Préchac (Gers) (32390)",
   "Préneron (32190)",
   "Pujaudran (32600)",
   "Puységur (32390)",
   "Ramouzens (32800)",
   "Razengues (32600)",
   "Riguepeu (32320)",
   "Roquebrune (Gers) (32190)",
   "Roquefort (Gers) (32390)",
   "Roquelaure-Saint-Aubin (32430)",
   "Roquepine (32100)",
   "Roques (Gers) (32310)",
   "Rozès (32190)",
   "Réans (32800)",
   "Réjaumont (Gers) (32390)",
   "Saint-Antoine (Gers) (32340)",
   "Saint-Antonin (Gers) (32120)",
   "Saint-Arailles (32350)",
   "Saint-Avit-Frandat (32700)",
   "Saint-Brès (Gers) (32120)",
   "Saint-Caprais (Gers) (32200)",
   "Saint-Clar (32380)",
   "Saint-Cricq (32430)",
   "Saint-Créac (Gers) (32380)",
   "Saint-Georges (Gers) (32430)",
   "Saint-Germier (Gers) (32200)",
   "Saint-Jean-Poutge (32190)",
   "Saint-Lary (Gers) (32360)",
   "Saint-Léonard (Gers) (32380)",
   "Saint-Martin-de-Goyne (32480)",
   "Saint-Mézard (32700)",
   "Saint-Orens (32120)",
   "Saint-Orens-Pouy-Petit (32100)",
   "Saint-Paul-de-Baïse (32190)",
   "Saint-Puy (32310)",
   "Saint-Sauvy (32270)",
   "Sainte-Anne (Gers) (32430)",
   "Sainte-Gemme (Gers) (32120)",
   "Sainte-Marie (Gers) (32200)",
   "Sainte-Mère (32700)",
   "Sainte-Radegonde (Gers) (32500)",
   "Sarrant (32120)",
   "Sempesserre (32700)",
   "Sirac (32430)",
   "Solomiac (32120)",
   "Séailles (32190)",
   "Ségoufielle (32600)",
   "Sérempuy (32120)",
   "Taybosc (32120)",
   "Terraube (32700)",
   "Thoux (32430)",
   "Touget (32430)",
   "Tournecoupe (32380)",
   "Tudelle (32190)",
   "Urdens (32500)",
   "Valence-sur-Baïse (32310)",
   "Vic-Fezensac (32190)"
  ],
  "departement": "Gers",
  "group": "Socialistes et apparentés",
  "nom": "Biémouret",
  "numCirco": "2",
  "numDepartement": "32",
  "prenom": "Gisèle"
 },
 "datan": "https://datan.fr/deputes/gers-32/depute_gisele-biemouret",
 "lcdg": {
  "siege": {
   "curAngleIndex": 42,
   "curRadiusIndex": 6,
   "id": "ai42ri6",
   "no": 515,
   "polar": {
    "angle": 2.489563989637195,
    "radius": 0.6875
   },
   "pos": {
    "x": -0.5464624284716805,
    "y": -0.4172575796519945
   }
  }
 },
 "nd_twitter": {
  "twitter": "GiseleBiemouret",
  "url_an": "http://www2.assemblee-nationale.fr/deputes/fiche/OMC_PA508"
 },
 "nosdeputes_link": "https://www.nosdeputes.fr/Gisèle-Biémouret",
 "official_link": "https://www2.assemblee-nationale.fr/deputes/fiche/OMC_PA508",
 "scrutins": {
  "VTANR5L15V1": "A",
  "VTANR5L15V1050": "P",
  "VTANR5L15V1051": "P",
  "VTANR5L15V1052": "P",
  "VTANR5L15V1053": "P",
  "VTANR5L15V1054": "P",
  "VTANR5L15V1055": "P",
  "VTANR5L15V1056": "P",
  "VTANR5L15V1057": "P",
  "VTANR5L15V1058": "P",
  "VTANR5L15V1059": "P",
  "VTANR5L15V106": "C",
  "VTANR5L15V1060": "P",
  "VTANR5L15V1061": "P",
  "VTANR5L15V1062": "P",
  "VTANR5L15V1063": "P",
  "VTANR5L15V1064": "P",
  "VTANR5L15V1065": "P",
  "VTANR5L15V1066": "P",
  "VTANR5L15V1067": "P",
  "VTANR5L15V1068": "P",
  "VTANR5L15V1071": "P",
  "VTANR5L15V1072": "P",
  "VTANR5L15V1073": "P",
  "VTANR5L15V1115": "P",
  "VTANR5L15V1171": "P",
  "VTANR5L15V118": "P",
  "VTANR5L15V1183": "P",
  "VTANR5L15V119": "P",
  "VTANR5L15V1197": "P",
  "VTANR5L15V1198": "P",
  "VTANR5L15V1199": "P",
  "VTANR5L15V120": "C",
  "VTANR5L15V1200": "P",
  "VTANR5L15V1201": "P",
  "VTANR5L15V1202": "P",
  "VTANR5L15V1203": "C",
  "VTANR5L15V1204": "P",
  "VTANR5L15V1205": "P",
  "VTANR5L15V1206": "P",
  "VTANR5L15V1207": "P",
  "VTANR5L15V1209": "C",
  "VTANR5L15V1263": "C",
  "VTANR5L15V1264": "P",
  "VTANR5L15V1265": "A",
  "VTANR5L15V1266": "A",
  "VTANR5L15V1267": "C",
  "VTANR5L15V1268": "P",
  "VTANR5L15V1269": "P",
  "VTANR5L15V1270": "C",
  "VTANR5L15V1271": "P",
  "VTANR5L15V1272": "C",
  "VTANR5L15V1273": "C",
  "VTANR5L15V1274": "P",
  "VTANR5L15V1275": "P",
  "VTANR5L15V1277": "P",
  "VTANR5L15V1278": "C",
  "VTANR5L15V1282": "P",
  "VTANR5L15V1283": "P",
  "VTANR5L15V1284": "P",
  "VTANR5L15V1285": "P",
  "VTANR5L15V1286": "P",
  "VTANR5L15V1287": "P",
  "VTANR5L15V1288": "P",
  "VTANR5L15V1289": "C",
  "VTANR5L15V1290": "P",
  "VTANR5L15V1292": "C",
  "VTANR5L15V1293": "P",
  "VTANR5L15V1295": "P",
  "VTANR5L15V1296": "P",
  "VTANR5L15V1299": "P",
  "VTANR5L15V1301": "P",
  "VTANR5L15V1302": "P",
  "VTANR5L15V1303": "P",
  "VTANR5L15V1304": "P",
  "VTANR5L15V1305": "P",
  "VTANR5L15V1306": "P",
  "VTANR5L15V1307": "P",
  "VTANR5L15V1308": "P",
  "VTANR5L15V1309": "P",
  "VTANR5L15V1310": "P",
  "VTANR5L15V1311": "P",
  "VTANR5L15V1313": "P",
  "VTANR5L15V1314": "P",
  "VTANR5L15V1315": "P",
  "VTANR5L15V1316": "P",
  "VTANR5L15V1317": "C",
  "VTANR5L15V1318": "P",
  "VTANR5L15V1319": "C",
  "VTANR5L15V1323": "P",
  "VTANR5L15V1324": "P",
  "VTANR5L15V1325": "P",
  "VTANR5L15V1326": "P",
  "VTANR5L15V1327": "P",
  "VTANR5L15V1328": "C",
  "VTANR5L15V1329": "P",
  "VTANR5L15V1330": "C",
  "VTANR5L15V1348": "C",
  "VTANR5L15V138": "P",
  "VTANR5L15V139": "P",
  "VTANR5L15V1429": "C",
  "VTANR5L15V1431": "C",
  "VTANR5L15V1432": "C",
  "VTANR5L15V1444": "C",
  "VTANR5L15V145": "P",
  "VTANR5L15V1483": "P",
  "VTANR5L15V1484": "P",
  "VTANR5L15V1485": "P",
  "VTANR5L15V1486": "P",
  "VTANR5L15V1487": "C",
  "VTANR5L15V1488": "C",
  "VTANR5L15V1489": "P",
  "VTANR5L15V1490": "P",
  "VTANR5L15V1491": "P",
  "VTANR5L15V1492": "C",
  "VTANR5L15V1495": "P",
  "VTANR5L15V1496": "P",
  "VTANR5L15V1497": "C",
  "VTANR5L15V1503": "P",
  "VTANR5L15V1504": "P",
  "VTANR5L15V1505": "C",
  "VTANR5L15V1506": "A",
  "VTANR5L15V1507": "C",
  "VTANR5L15V1508": "P",
  "VTANR5L15V1509": "P",
  "VTANR5L15V1510": "P",
  "VTANR5L15V1511": "P",
  "VTANR5L15V1536": "C",
  "VTANR5L15V1540": "P",
  "VTANR5L15V1541": "C",
  "VTANR5L15V1543": "C",
  "VTANR5L15V1544": "C",
  "VTANR5L15V1545": "C",
  "VTANR5L15V1546": "C",
  "VTANR5L15V1547": "C",
  "VTANR5L15V1548": "C",
  "VTANR5L15V1549": "P",
  "VTANR5L15V1573": "P",
  "VTANR5L15V1633": "C",
  "VTANR5L15V1634": "C",
  "VTANR5L15V1662": "C",
  "VTANR5L15V1709": "C",
  "VTANR5L15V1711": "C",
  "VTANR5L15V1716": "C",
  "VTANR5L15V1717": "C",
  "VTANR5L15V1718": "C",
  "VTANR5L15V1719": "A",
  "VTANR5L15V1763": "P",
  "VTANR5L15V1764": "P",
  "VTANR5L15V1765": "P",
  "VTANR5L15V1767": "P",
  "VTANR5L15V1768": "P",
  "VTANR5L15V1769": "C",
  "VTANR5L15V1773": "P",
  "VTANR5L15V1774": "P",
  "VTANR5L15V1775": "P",
  "VTANR5L15V1776": "P",
  "VTANR5L15V1777": "P",
  "VTANR5L15V1778": "P",
  "VTANR5L15V1779": "P",
  "VTANR5L15V1780": "P",
  "VTANR5L15V1781": "P",
  "VTANR5L15V1782": "P",
  "VTANR5L15V1783": "P",
  "VTANR5L15V1784": "P",
  "VTANR5L15V1785": "P",
  "VTANR5L15V1786": "P",
  "VTANR5L15V1787": "P",
  "VTANR5L15V1788": "P",
  "VTANR5L15V1789": "P",
  "VTANR5L15V1790": "P",
  "VTANR5L15V1791": "P",
  "VTANR5L15V1792": "P",
  "VTANR5L15V1793": "C",
  "VTANR5L15V1794": "C",
  "VTANR5L15V1795": "C",
  "VTANR5L15V1798": "P",
  "VTANR5L15V1799": "P",
  "VTANR5L15V1800": "A",
  "VTANR5L15V1801": "A",
  "VTANR5L15V1802": "P",
  "VTANR5L15V1803": "P",
  "VTANR5L15V1804": "C",
  "VTANR5L15V1805": "P",
  "VTANR5L15V1806": "P",
  "VTANR5L15V1807": "C",
  "VTANR5L15V1808": "P",
  "VTANR5L15V1809": "P",
  "VTANR5L15V1810": "P",
  "VTANR5L15V1811": "P",
  "VTANR5L15V1812": "P",
  "VTANR5L15V1813": "P",
  "VTANR5L15V1814": "C",
  "VTANR5L15V183": "C",
  "VTANR5L15V1839": "C",
  "VTANR5L15V184": "C",
  "VTANR5L15V1840": "C",
  "VTANR5L15V1842": "P",
  "VTANR5L15V1843": "P",
  "VTANR5L15V1844": "P",
  "VTANR5L15V1845": "P",
  "VTANR5L15V1846": "P",
  "VTANR5L15V1847": "C",
  "VTANR5L15V1848": "P",
  "VTANR5L15V1850": "C",
  "VTANR5L15V187": "P",
  "VTANR5L15V188": "C",
  "VTANR5L15V189": "P",
  "VTANR5L15V190": "P",
  "VTANR5L15V191": "P",
  "VTANR5L15V1912": "A",
  "VTANR5L15V192": "P",
  "VTANR5L15V1923": "C",
  "VTANR5L15V1928": "C",
  "VTANR5L15V1929": "P",
  "VTANR5L15V193": "P",
  "VTANR5L15V194": "P",
  "VTANR5L15V1941": "C",
  "VTANR5L15V1957": "A",
  "VTANR5L15V198": "C",
  "VTANR5L15V1988": "A",
  "VTANR5L15V199": "C",
  "VTANR5L15V200": "A",
  "VTANR5L15V202": "P",
  "VTANR5L15V203": "C",
  "VTANR5L15V2039": "A",
  "VTANR5L15V204": "P",
  "VTANR5L15V2042": "C",
  "VTANR5L15V205": "P",
  "VTANR5L15V2051": "P",
  "VTANR5L15V2052": "P",
  "VTANR5L15V2053": "P",
  "VTANR5L15V2054": "C",
  "VTANR5L15V2059": "C",
  "VTANR5L15V206": "C",
  "VTANR5L15V207": "C",
  "VTANR5L15V2071": "A",
  "VTANR5L15V2078": "A",
  "VTANR5L15V2079": "A",
  "VTANR5L15V208": "C",
  "VTANR5L15V2105": "C",
  "VTANR5L15V2130": "P",
  "VTANR5L15V2131": "P",
  "VTANR5L15V2146": "P",
  "VTANR5L15V2147": "P",
  "VTANR5L15V2177": "C",
  "VTANR5L15V2178": "P",
  "VTANR5L15V2179": "P",
  "VTANR5L15V2180": "C",
  "VTANR5L15V2181": "C",
  "VTANR5L15V2182": "P",
  "VTANR5L15V2183": "A",
  "VTANR5L15V2184": "A",
  "VTANR5L15V2185": "P",
  "VTANR5L15V2186": "P",
  "VTANR5L15V2187": "P",
  "VTANR5L15V2188": "P",
  "VTANR5L15V2189": "P",
  "VTANR5L15V2190": "P",
  "VTANR5L15V2191": "C",
  "VTANR5L15V2193": "C",
  "VTANR5L15V2194": "C",
  "VTANR5L15V2195": "C",
  "VTANR5L15V2196": "A",
  "VTANR5L15V2197": "P",
  "VTANR5L15V2198": "P",
  "VTANR5L15V2201": "P",
  "VTANR5L15V2202": "P",
  "VTANR5L15V2206": "P",
  "VTANR5L15V2209": "C",
  "VTANR5L15V2210": "P",
  "VTANR5L15V2213": "P",
  "VTANR5L15V2214": "P",
  "VTANR5L15V2215": "C",
  "VTANR5L15V2216": "P",
  "VTANR5L15V2217": "P",
  "VTANR5L15V2218": "P",
  "VTANR5L15V2219": "P",
  "VTANR5L15V2220": "P",
  "VTANR5L15V2221": "P",
  "VTANR5L15V2222": "P",
  "VTANR5L15V2223": "P",
  "VTANR5L15V2224": "P",
  "VTANR5L15V2225": "P",
  "VTANR5L15V2226": "P",
  "VTANR5L15V2227": "P",
  "VTANR5L15V2228": "P",
  "VTANR5L15V2229": "P",
  "VTANR5L15V2230": "P",
  "VTANR5L15V2235": "C",
  "VTANR5L15V2270": "A",
  "VTANR5L15V2307": "C",
  "VTANR5L15V2329": "A",
  "VTANR5L15V2330": "P",
  "VTANR5L15V2331": "P",
  "VTANR5L15V2332": "P",
  "VTANR5L15V2333": "C",
  "VTANR5L15V2334": "P",
  "VTANR5L15V2337": "C",
  "VTANR5L15V242": "P",
  "VTANR5L15V243": "P",
  "VTANR5L15V244": "P",
  "VTANR5L15V245": "P",
  "VTANR5L15V2460": "P",
  "VTANR5L15V2461": "P",
  "VTANR5L15V2462": "P",
  "VTANR5L15V2463": "P",
  "VTANR5L15V2464": "P",
  "VTANR5L15V2465": "P",
  "VTANR5L15V2466": "P",
  "VTANR5L15V2467": "P",
  "VTANR5L15V2468": "P",
  "VTANR5L15V2469": "P",
  "VTANR5L15V2470": "P",
  "VTANR5L15V2471": "P",
  "VTANR5L15V2472": "P",
  "VTANR5L15V2473": "P",
  "VTANR5L15V2474": "P",
  "VTANR5L15V2475": "P",
  "VTANR5L15V2476": "P",
  "VTANR5L15V2477": "P",
  "VTANR5L15V2478": "P",
  "VTANR5L15V2479": "P",
  "VTANR5L15V2480": "P",
  "VTANR5L15V2481": "P",
  "VTANR5L15V2482": "P",
  "VTANR5L15V2484": "P",
  "VTANR5L15V2485": "P",
  "VTANR5L15V2486": "P",
  "VTANR5L15V2487": "P",
  "VTANR5L15V2488": "P",
  "VTANR5L15V2489": "P",
  "VTANR5L15V2490": "P",
  "VTANR5L15V2491": "P",
  "VTANR5L15V2492": "P",
  "VTANR5L15V2501": "P",
  "VTANR5L15V2502": "P",
  "VTANR5L15V2503": "P",
  "VTANR5L15V2504": "P",
  "VTANR5L15V2505": "P",
  "VTANR5L15V2506": "P",
  "VTANR5L15V2507": "P",
  "VTANR5L15V2509": "P",
  "VTANR5L15V2510": "P",
  "VTANR5L15V2511": "P",
  "VTANR5L15V2512": "P",
  "VTANR5L15V2513": "P",
  "VTANR5L15V2515": "P",
  "VTANR5L15V2516": "P",
  "VTANR5L15V2517": "P",
  "VTANR5L15V2518": "P",
  "VTANR5L15V2519": "P",
  "VTANR5L15V2520": "P",
  "VTANR5L15V2521": "P",
  "VTANR5L15V2522": "P",
  "VTANR5L15V2523": "P",
  "VTANR5L15V2524": "P",
  "VTANR5L15V2618": "P",
  "VTANR5L15V2619": "P",
  "VTANR5L15V2622": "P",
  "VTANR5L15V2623": "P",
  "VTANR5L15V2624": "P",
  "VTANR5L15V2626": "P",
  "VTANR5L15V2627": "P",
  "VTANR5L15V2628": "P",
  "VTANR5L15V2629": "P",
  "VTANR5L15V2639": "P",
  "VTANR5L15V2640": "P",
  "VTANR5L15V2641": "P",
  "VTANR5L15V2707": "P",
  "VTANR5L15V272": "C",
  "VTANR5L15V2733": "P",
  "VTANR5L15V2734": "A",
  "VTANR5L15V2735": "A",
  "VTANR5L15V2736": "A",
  "VTANR5L15V2737": "P",
  "VTANR5L15V2738": "P",
  "VTANR5L15V2739": "C",
  "VTANR5L15V2740": "C",
  "VTANR5L15V2741": "C",
  "VTANR5L15V2742": "A",
  "VTANR5L15V2743": "C",
  "VTANR5L15V2744": "P",
  "VTANR5L15V2745": "P",
  "VTANR5L15V2746": "C",
  "VTANR5L15V2747": "P",
  "VTANR5L15V2748": "P",
  "VTANR5L15V2749": "C",
  "VTANR5L15V2750": "C",
  "VTANR5L15V2751": "A",
  "VTANR5L15V2752": "A",
  "VTANR5L15V2753": "P",
  "VTANR5L15V2754": "C",
  "VTANR5L15V2755": "C",
  "VTANR5L15V2756": "C",
  "VTANR5L15V2757": "P",
  "VTANR5L15V2758": "C",
  "VTANR5L15V2759": "P",
  "VTANR5L15V2760": "P",
  "VTANR5L15V2761": "P",
  "VTANR5L15V2762": "P",
  "VTANR5L15V2801": "P",
  "VTANR5L15V2802": "P",
  "VTANR5L15V2803": "P",
  "VTANR5L15V2804": "P",
  "VTANR5L15V2808": "P",
  "VTANR5L15V2814": "C",
  "VTANR5L15V2820": "C",
  "VTANR5L15V2821": "C",
  "VTANR5L15V2822": "P",
  "VTANR5L15V2823": "P",
  "VTANR5L15V2824": "P",
  "VTANR5L15V2825": "P",
  "VTANR5L15V2826": "P",
  "VTANR5L15V2827": "C",
  "VTANR5L15V2828": "P",
  "VTANR5L15V2829": "C",
  "VTANR5L15V2830": "P",
  "VTANR5L15V2857": "P",
  "VTANR5L15V2858": "A",
  "VTANR5L15V2859": "P",
  "VTANR5L15V2860": "P",
  "VTANR5L15V2861": "P",
  "VTANR5L15V2862": "P",
  "VTANR5L15V2863": "P",
  "VTANR5L15V2864": "P",
  "VTANR5L15V2865": "P",
  "VTANR5L15V291": "P",
  "VTANR5L15V2940": "C",
  "VTANR5L15V2991": "C",
  "VTANR5L15V2992": "P",
  "VTANR5L15V2993": "P",
  "VTANR5L15V2994": "P",
  "VTANR5L15V2995": "P",
  "VTANR5L15V2996": "P",
  "VTANR5L15V2997": "P",
  "VTANR5L15V2999": "C",
  "VTANR5L15V3000": "C",
  "VTANR5L15V3001": "C",
  "VTANR5L15V3002": "C",
  "VTANR5L15V3003": "P",
  "VTANR5L15V3004": "P",
  "VTANR5L15V3005": "P",
  "VTANR5L15V3006": "P",
  "VTANR5L15V3007": "P",
  "VTANR5L15V3008": "P",
  "VTANR5L15V3009": "C",
  "VTANR5L15V3013": "P",
  "VTANR5L15V3014": "P",
  "VTANR5L15V3015": "P",
  "VTANR5L15V3020": "P",
  "VTANR5L15V3023": "P",
  "VTANR5L15V3024": "C",
  "VTANR5L15V3025": "P",
  "VTANR5L15V3026": "P",
  "VTANR5L15V3027": "C",
  "VTANR5L15V3059": "C",
  "VTANR5L15V3066": "P",
  "VTANR5L15V3088": "P",
  "VTANR5L15V3089": "P",
  "VTANR5L15V3090": "P",
  "VTANR5L15V3091": "P",
  "VTANR5L15V3092": "P",
  "VTANR5L15V3093": "P",
  "VTANR5L15V3094": "P",
  "VTANR5L15V3095": "P",
  "VTANR5L15V3096": "P",
  "VTANR5L15V3097": "P",
  "VTANR5L15V3098": "P",
  "VTANR5L15V3099": "P",
  "VTANR5L15V3100": "P",
  "VTANR5L15V3101": "P",
  "VTANR5L15V3102": "P",
  "VTANR5L15V3104": "P",
  "VTANR5L15V3105": "P",
  "VTANR5L15V3106": "P",
  "VTANR5L15V3107": "P",
  "VTANR5L15V3108": "P",
  "VTANR5L15V3109": "C",
  "VTANR5L15V3110": "P",
  "VTANR5L15V3112": "C",
  "VTANR5L15V3136": "P",
  "VTANR5L15V3137": "P",
  "VTANR5L15V3138": "P",
  "VTANR5L15V3139": "P",
  "VTANR5L15V314": "C",
  "VTANR5L15V3140": "P",
  "VTANR5L15V3141": "P",
  "VTANR5L15V3142": "P",
  "VTANR5L15V3143": "P",
  "VTANR5L15V3163": "P",
  "VTANR5L15V3164": "P",
  "VTANR5L15V3165": "P",
  "VTANR5L15V3166": "P",
  "VTANR5L15V3167": "C",
  "VTANR5L15V3186": "C",
  "VTANR5L15V3247": "C",
  "VTANR5L15V3248": "P",
  "VTANR5L15V3249": "C",
  "VTANR5L15V3250": "P",
  "VTANR5L15V3251": "C",
  "VTANR5L15V3254": "C",
  "VTANR5L15V3255": "A",
  "VTANR5L15V3256": "C",
  "VTANR5L15V3268": "P",
  "VTANR5L15V3269": "C",
  "VTANR5L15V3270": "P",
  "VTANR5L15V3271": "P",
  "VTANR5L15V3272": "P",
  "VTANR5L15V3276": "P",
  "VTANR5L15V3277": "P",
  "VTANR5L15V3278": "P",
  "VTANR5L15V3283": "P",
  "VTANR5L15V3284": "P",
  "VTANR5L15V3308": "P",
  "VTANR5L15V3326": "P",
  "VTANR5L15V3327": "P",
  "VTANR5L15V3329": "A",
  "VTANR5L15V3378": "C",
  "VTANR5L15V3420": "C",
  "VTANR5L15V3421": "A",
  "VTANR5L15V3422": "P",
  "VTANR5L15V3423": "C",
  "VTANR5L15V3424": "C",
  "VTANR5L15V3425": "P",
  "VTANR5L15V3426": "P",
  "VTANR5L15V3427": "P",
  "VTANR5L15V3428": "P",
  "VTANR5L15V3429": "C",
  "VTANR5L15V3430": "A",
  "VTANR5L15V3431": "C",
  "VTANR5L15V3432": "C",
  "VTANR5L15V3433": "C",
  "VTANR5L15V3434": "P",
  "VTANR5L15V3435": "P",
  "VTANR5L15V3436": "P",
  "VTANR5L15V3437": "P",
  "VTANR5L15V3438": "P",
  "VTANR5L15V3440": "P",
  "VTANR5L15V3441": "C",
  "VTANR5L15V3442": "C",
  "VTANR5L15V3443": "C",
  "VTANR5L15V345": "C",
  "VTANR5L15V3454": "P",
  "VTANR5L15V347": "P",
  "VTANR5L15V3484": "P",
  "VTANR5L15V3488": "P",
  "VTANR5L15V3489": "P",
  "VTANR5L15V3490": "C",
  "VTANR5L15V3491": "P",
  "VTANR5L15V3492": "C",
  "VTANR5L15V351": "C",
  "VTANR5L15V3539": "P",
  "VTANR5L15V3540": "P",
  "VTANR5L15V3541": "P",
  "VTANR5L15V3542": "C",
  "VTANR5L15V3543": "P",
  "VTANR5L15V3544": "C",
  "VTANR5L15V3545": "P",
  "VTANR5L15V3546": "C",
  "VTANR5L15V3547": "P",
  "VTANR5L15V3567": "C",
  "VTANR5L15V3568": "P",
  "VTANR5L15V3569": "P",
  "VTANR5L15V3570": "C",
  "VTANR5L15V358": "C",
  "VTANR5L15V3633": "P",
  "VTANR5L15V3641": "C",
  "VTANR5L15V365": "P",
  "VTANR5L15V3738": "C",
  "VTANR5L15V389": "P",
  "VTANR5L15V407": "C",
  "VTANR5L15V419": "P",
  "VTANR5L15V433": "A",
  "VTANR5L15V438": "P",
  "VTANR5L15V439": "C",
  "VTANR5L15V477": "C",
  "VTANR5L15V478": "C",
  "VTANR5L15V479": "P",
  "VTANR5L15V480": "P",
  "VTANR5L15V481": "P",
  "VTANR5L15V482": "P",
  "VTANR5L15V483": "C",
  "VTANR5L15V484": "C",
  "VTANR5L15V490": "P",
  "VTANR5L15V491": "P",
  "VTANR5L15V493": "A",
  "VTANR5L15V494": "P",
  "VTANR5L15V495": "P",
  "VTANR5L15V497": "P",
  "VTANR5L15V498": "P",
  "VTANR5L15V499": "C",
  "VTANR5L15V500": "A",
  "VTANR5L15V501": "P",
  "VTANR5L15V503": "P",
  "VTANR5L15V505": "C",
  "VTANR5L15V506": "C",
  "VTANR5L15V507": "C",
  "VTANR5L15V508": "P",
  "VTANR5L15V509": "P",
  "VTANR5L15V510": "A",
  "VTANR5L15V512": "P",
  "VTANR5L15V515": "C",
  "VTANR5L15V516": "C",
  "VTANR5L15V517": "C",
  "VTANR5L15V518": "P",
  "VTANR5L15V519": "C",
  "VTANR5L15V520": "P",
  "VTANR5L15V521": "C",
  "VTANR5L15V522": "P",
  "VTANR5L15V523": "P",
  "VTANR5L15V524": "P",
  "VTANR5L15V528": "P",
  "VTANR5L15V529": "C",
  "VTANR5L15V530": "C",
  "VTANR5L15V531": "P",
  "VTANR5L15V532": "P",
  "VTANR5L15V533": "C",
  "VTANR5L15V534": "C",
  "VTANR5L15V537": "C",
  "VTANR5L15V538": "C",
  "VTANR5L15V539": "C",
  "VTANR5L15V540": "C",
  "VTANR5L15V541": "C",
  "VTANR5L15V542": "P",
  "VTANR5L15V549": "P",
  "VTANR5L15V550": "P",
  "VTANR5L15V551": "P",
  "VTANR5L15V553": "A",
  "VTANR5L15V554": "C",
  "VTANR5L15V555": "C",
  "VTANR5L15V559": "C",
  "VTANR5L15V560": "C",
  "VTANR5L15V561": "C",
  "VTANR5L15V562": "C",
  "VTANR5L15V563": "P",
  "VTANR5L15V564": "C",
  "VTANR5L15V566": "C",
  "VTANR5L15V567": "C",
  "VTANR5L15V568": "C",
  "VTANR5L15V569": "C",
  "VTANR5L15V570": "C",
  "VTANR5L15V571": "C",
  "VTANR5L15V572": "P",
  "VTANR5L15V576": "P",
  "VTANR5L15V577": "P",
  "VTANR5L15V578": "C",
  "VTANR5L15V581": "C",
  "VTANR5L15V582": "C",
  "VTANR5L15V585": "P",
  "VTANR5L15V586": "P",
  "VTANR5L15V587": "P",
  "VTANR5L15V588": "P",
  "VTANR5L15V589": "P",
  "VTANR5L15V590": "P",
  "VTANR5L15V591": "P",
  "VTANR5L15V592": "P",
  "VTANR5L15V593": "P",
  "VTANR5L15V594": "P",
  "VTANR5L15V595": "P",
  "VTANR5L15V596": "P",
  "VTANR5L15V597": "P",
  "VTANR5L15V598": "C",
  "VTANR5L15V60": "P",
  "VTANR5L15V61": "P",
  "VTANR5L15V611": "P",
  "VTANR5L15V615": "P",
  "VTANR5L15V616": "P",
  "VTANR5L15V617": "P",
  "VTANR5L15V618": "P",
  "VTANR5L15V619": "C",
  "VTANR5L15V62": "P",
  "VTANR5L15V64": "P",
  "VTANR5L15V65": "P",
  "VTANR5L15V66": "P",
  "VTANR5L15V67": "P",
  "VTANR5L15V70": "P",
  "VTANR5L15V71": "P",
  "VTANR5L15V72": "P",
  "VTANR5L15V729": "C",
  "VTANR5L15V928": "C",
  "VTANR5L15V929": "P",
  "VTANR5L15V930": "P",
  "VTANR5L15V931": "P",
  "VTANR5L15V932": "P",
  "VTANR5L15V933": "P",
  "VTANR5L15V934": "P",
  "VTANR5L15V935": "C",
  "VTANR5L15V936": "P",
  "VTANR5L15V937": "P",
  "VTANR5L15V939": "P",
  "VTANR5L15V940": "C",
  "VTANR5L15V941": "P",
  "VTANR5L15V942": "C",
  "VTANR5L15V943": "P",
  "VTANR5L15V944": "P",
  "VTANR5L15V945": "C",
  "VTANR5L15V947": "P",
  "VTANR5L15V948": "P",
  "VTANR5L15V950": "C",
  "VTANR5L15V951": "P",
  "VTANR5L15V952": "C",
  "VTANR5L15V953": "C",
  "VTANR5L15V954": "P",
  "VTANR5L15V956": "C",
  "VTANR5L15V957": "P",
  "VTANR5L15V958": "P",
  "VTANR5L15V959": "P",
  "VTANR5L15V960": "P",
  "VTANR5L15V961": "C",
  "VTANR5L15V965": "C",
  "VTANR5L15V966": "C",
  "VTANR5L15V967": "P",
  "VTANR5L15V968": "C",
  "VTANR5L15V969": "C",
  "VTANR5L15V970": "P",
  "VTANR5L15V971": "C",
  "VTANR5L15V972": "C",
  "VTANR5L15V974": "C",
  "VTANR5L15V976": "P"
 },
 "twitter": {
  "id": "947822287",
  "name": "GiseleBiemouret",
  "public_metrics": {
   "followers_count": 3624,
   "following_count": 1036,
   "listed_count": 135,
   "tweet_count": 2807
  },
  "username": "GiseleBiemouret"
 },
 "twitter_username": {
  "status": "found",
  "value": "GiseleBiemouret"
 },
 "uid": "PA508"
}