{
 "an_data_depute": {},
 "an_www_depute": {
  "groupe": "Horizons et apparentés",
  "imgurl": "https://www2.assemblee-nationale.fr/static/tribun/16/photos/605782.jpg",
  "nosiege": "187"
 },
 "an_www_pic": {},
 "an_www_social": {},
 "lcdg": {
  "siege": {
   "curAngleIndex": 13,
   "curRadiusIndex": 6,
   "id": "ai13ri6",
   "no": 187,
   "polar": {
    "angle": 0.7705793301257984,
    "radius": 0.6875
   },
   "pos": {
    "x": 0.4932862392179777,
    "y": -0.4789735112849187
   }
  }
 },
 "nd_twitter": {
  "twitter": "LMarcangeli",
  "url_an": "https://www2.assemblee-nationale.fr/deputes/fiche/OMC_PA605782"
 },
 "official_link": "https://www2.assemblee-nationale.fr/deputes/fiche/OMC_PA605782",
 "uid": "PA605782"
}