{
 "an_data_depute": {
  "dateNais": "1989-06-28",
  "femme": false,
  "ident": {
   "alpha": "AdamD",
   "civ": "M.",
   "nom": "Adam",
   "prenom": "Damien",
   "trigramme": "DAD"
  },
  "nom": "Damien Adam"
 },
 "an_www_depute": {
  "groupe": "La République en Marche",
  "imgurl": "https://www2.assemblee-nationale.fr/static/tribun/15/photos/722038.jpg",
  "nosiege": "319"
 },
 "an_www_pic": {},
 "an_www_social": {
  "facebook_link": "https://fr-fr.facebook.com/damienadam76/",
  "twitter_link": "https://twitter.com/@damienadam76/"
 },
 "circo": {
  "acteurId": "OMC_PA722038",
  "civ": "M.",
  "communes": [
   "Déville-lès-Rouen (76250)",
   "Mont-Saint-Aignan (76130)",
   "Rouen (76000)",
   "Rouen (76100)"
  ],
  "departement": "Seine-maritime",
  "group": "La République en Marche",
  "nom": "Adam",
  "numCirco": "1",
  "numDepartement": "76",
  "prenom": "Damien"
 },
 "datan": "https://datan.fr/deputes/seine-maritime-76/depute_damien-adam",
 "lcdg": {
  "siege": {
   "curAngleIndex": 31,
   "curRadiusIndex": 11,
   "id": "ai31ri11",
   "no": 319,
   "polar": {
    "angle": 1.232776864066881,
    "radius": 1
   },
   "pos": {
    "x": 0.3316192785520677,
    "y": -0.9435998213157802
   }
  }
 },
 "nd_twitter": {
  "twitter": "damienadam76",
  "url_an": "http://www2.assemblee-nationale.fr/deputes/fiche/OMC_PA722038"
 },
 "nosdeputes_link": "https://www.nosdeputes.fr/Damien-Adam",
 "official_link": "https://www2.assemblee-nationale.fr/deputes/fiche/OMC_PA722038",
 "scrutins": {
  "VTANR5L15V1": "P",
  "VTANR5L15V10": "C",
  "VTANR5L15V1010": "C",
  "VTANR5L15V1011": "C",
  "VTANR5L15V103": "P",
  "VTANR5L15V104": "P",
  "VTANR5L15V105": "C",
  "VTANR5L15V106": "P",
  "VTANR5L15V107": "P",
  "VTANR5L15V11": "C",
  "VTANR5L15V1119": "C",
  "VTANR5L15V1125": "P",
  "VTANR5L15V1126": "C",
  "VTANR5L15V1127": "P",
  "VTANR5L15V1128": "C",
  "VTANR5L15V1129": "P",
  "VTANR5L15V1171": "P",
  "VTANR5L15V1181": "P",
  "VTANR5L15V1182": "P",
  "VTANR5L15V119": "P",
  "VTANR5L15V12": "C",
  "VTANR5L15V120": "C",
  "VTANR5L15V1209": "P",
  "VTANR5L15V1216": "P",
  "VTANR5L15V1217": "P",
  "VTANR5L15V1218": "P",
  "VTANR5L15V122": "P",
  "VTANR5L15V123": "C",
  "VTANR5L15V124": "C",
  "VTANR5L15V126": "P",
  "VTANR5L15V1263": "P",
  "VTANR5L15V1266": "C",
  "VTANR5L15V1268": "C",
  "VTANR5L15V1269": "C",
  "VTANR5L15V1270": "P",
  "VTANR5L15V1279": "C",
  "VTANR5L15V1280": "C",
  "VTANR5L15V1281": "C",
  "VTANR5L15V1282": "C",
  "VTANR5L15V13": "C",
  "VTANR5L15V131": "C",
  "VTANR5L15V1330": "P",
  "VTANR5L15V1345": "C",
  "VTANR5L15V138": "P",
  "VTANR5L15V139": "P",
  "VTANR5L15V1393": "C",
  "VTANR5L15V1394": "C",
  "VTANR5L15V1395": "C",
  "VTANR5L15V1396": "C",
  "VTANR5L15V1397": "C",
  "VTANR5L15V14": "C",
  "VTANR5L15V142": "P",
  "VTANR5L15V1429": "P",
  "VTANR5L15V143": "P",
  "VTANR5L15V1432": "P",
  "VTANR5L15V144": "P",
  "VTANR5L15V145": "C",
  "VTANR5L15V15": "C",
  "VTANR5L15V1536": "P",
  "VTANR5L15V154": "P",
  "VTANR5L15V155": "C",
  "VTANR5L15V1586": "P",
  "VTANR5L15V1587": "A",
  "VTANR5L15V1593": "P",
  "VTANR5L15V1594": "C",
  "VTANR5L15V1595": "P",
  "VTANR5L15V1596": "P",
  "VTANR5L15V1599": "C",
  "VTANR5L15V16": "C",
  "VTANR5L15V1600": "C",
  "VTANR5L15V1601": "C",
  "VTANR5L15V1602": "P",
  "VTANR5L15V1603": "C",
  "VTANR5L15V1604": "P",
  "VTANR5L15V1633": "P",
  "VTANR5L15V1634": "P",
  "VTANR5L15V1641": "C",
  "VTANR5L15V1645": "P",
  "VTANR5L15V1646": "C",
  "VTANR5L15V1647": "C",
  "VTANR5L15V1662": "P",
  "VTANR5L15V17": "C",
  "VTANR5L15V1709": "P",
  "VTANR5L15V1711": "P",
  "VTANR5L15V1712": "P",
  "VTANR5L15V1716": "A",
  "VTANR5L15V18": "C",
  "VTANR5L15V1814": "P",
  "VTANR5L15V183": "P",
  "VTANR5L15V1839": "P",
  "VTANR5L15V184": "P",
  "VTANR5L15V1840": "P",
  "VTANR5L15V19": "C",
  "VTANR5L15V1912": "P",
  "VTANR5L15V1923": "P",
  "VTANR5L15V1926": "P",
  "VTANR5L15V1934": "P",
  "VTANR5L15V1935": "P",
  "VTANR5L15V1936": "P",
  "VTANR5L15V1937": "P",
  "VTANR5L15V1938": "P",
  "VTANR5L15V1941": "P",
  "VTANR5L15V1957": "P",
  "VTANR5L15V1958": "C",
  "VTANR5L15V1988": "P",
  "VTANR5L15V1989": "C",
  "VTANR5L15V1990": "C",
  "VTANR5L15V1991": "C",
  "VTANR5L15V1992": "P",
  "VTANR5L15V1993": "C",
  "VTANR5L15V1994": "P",
  "VTANR5L15V1995": "C",
  "VTANR5L15V1996": "P",
  "VTANR5L15V1997": "P",
  "VTANR5L15V1998": "C",
  "VTANR5L15V1999": "C",
  "VTANR5L15V2": "P",
  "VTANR5L15V20": "C",
  "VTANR5L15V2000": "C",
  "VTANR5L15V2001": "P",
  "VTANR5L15V2002": "A",
  "VTANR5L15V2003": "P",
  "VTANR5L15V2004": "P",
  "VTANR5L15V2039": "P",
  "VTANR5L15V2051": "C",
  "VTANR5L15V2052": "C",
  "VTANR5L15V2057": "C",
  "VTANR5L15V2058": "P",
  "VTANR5L15V2059": "P",
  "VTANR5L15V2065": "P",
  "VTANR5L15V2071": "P",
  "VTANR5L15V2078": "P",
  "VTANR5L15V2079": "P",
  "VTANR5L15V208": "P",
  "VTANR5L15V21": "C",
  "VTANR5L15V212": "C",
  "VTANR5L15V213": "C",
  "VTANR5L15V2130": "P",
  "VTANR5L15V2131": "P",
  "VTANR5L15V2146": "P",
  "VTANR5L15V2147": "P",
  "VTANR5L15V216": "P",
  "VTANR5L15V2177": "P",
  "VTANR5L15V22": "C",
  "VTANR5L15V2235": "P",
  "VTANR5L15V2245": "C",
  "VTANR5L15V2246": "C",
  "VTANR5L15V2247": "C",
  "VTANR5L15V2248": "P",
  "VTANR5L15V2249": "C",
  "VTANR5L15V2250": "C",
  "VTANR5L15V23": "P",
  "VTANR5L15V2307": "P",
  "VTANR5L15V2329": "P",
  "VTANR5L15V2331": "C",
  "VTANR5L15V2332": "C",
  "VTANR5L15V2335": "P",
  "VTANR5L15V2337": "P",
  "VTANR5L15V2346": "P",
  "VTANR5L15V2360": "C",
  "VTANR5L15V2388": "P",
  "VTANR5L15V2389": "C",
  "VTANR5L15V2390": "C",
  "VTANR5L15V2391": "C",
  "VTANR5L15V2392": "C",
  "VTANR5L15V2393": "C",
  "VTANR5L15V2394": "C",
  "VTANR5L15V2395": "C",
  "VTANR5L15V2396": "C",
  "VTANR5L15V2397": "C",
  "VTANR5L15V2398": "C",
  "VTANR5L15V2399": "C",
  "VTANR5L15V24": "C",
  "VTANR5L15V2400": "C",
  "VTANR5L15V2401": "C",
  "VTANR5L15V2402": "P",
  "VTANR5L15V2403": "C",
  "VTANR5L15V2410": "A",
  "VTANR5L15V2411": "C",
  "VTANR5L15V2412": "P",
  "VTANR5L15V2413": "P",
  "VTANR5L15V2420": "P",
  "VTANR5L15V2448": "P",
  "VTANR5L15V2449": "C",
  "VTANR5L15V2463": "C",
  "VTANR5L15V2464": "C",
  "VTANR5L15V2465": "C",
  "VTANR5L15V2466": "C",
  "VTANR5L15V2467": "C",
  "VTANR5L15V2468": "C",
  "VTANR5L15V2474": "C",
  "VTANR5L15V2475": "C",
  "VTANR5L15V2476": "C",
  "VTANR5L15V2477": "C",
  "VTANR5L15V2478": "C",
  "VTANR5L15V2479": "C",
  "VTANR5L15V2486": "C",
  "VTANR5L15V2487": "C",
  "VTANR5L15V2488": "C",
  "VTANR5L15V2489": "C",
  "VTANR5L15V2490": "C",
  "VTANR5L15V2491": "C",
  "VTANR5L15V2492": "C",
  "VTANR5L15V2493": "C",
  "VTANR5L15V2494": "C",
  "VTANR5L15V2495": "C",
  "VTANR5L15V2496": "C",
  "VTANR5L15V2497": "C",
  "VTANR5L15V2498": "C",
  "VTANR5L15V2499": "C",
  "VTANR5L15V25": "C",
  "VTANR5L15V2500": "C",
  "VTANR5L15V2501": "C",
  "VTANR5L15V2502": "C",
  "VTANR5L15V2503": "C",
  "VTANR5L15V2504": "C",
  "VTANR5L15V2505": "C",
  "VTANR5L15V2506": "C",
  "VTANR5L15V2507": "C",
  "VTANR5L15V2508": "C",
  "VTANR5L15V2565": "C",
  "VTANR5L15V2568": "C",
  "VTANR5L15V2569": "C",
  "VTANR5L15V257": "C",
  "VTANR5L15V2570": "C",
  "VTANR5L15V2571": "C",
  "VTANR5L15V2572": "C",
  "VTANR5L15V2573": "C",
  "VTANR5L15V2574": "C",
  "VTANR5L15V2575": "C",
  "VTANR5L15V2576": "C",
  "VTANR5L15V2577": "C",
  "VTANR5L15V2578": "C",
  "VTANR5L15V2579": "C",
  "VTANR5L15V258": "P",
  "VTANR5L15V2580": "C",
  "VTANR5L15V2581": "C",
  "VTANR5L15V2582": "C",
  "VTANR5L15V2583": "P",
  "VTANR5L15V2584": "C",
  "VTANR5L15V2585": "C",
  "VTANR5L15V2587": "C",
  "VTANR5L15V259": "C",
  "VTANR5L15V2595": "C",
  "VTANR5L15V2596": "C",
  "VTANR5L15V2597": "C",
  "VTANR5L15V2598": "C",
  "VTANR5L15V2599": "C",
  "VTANR5L15V26": "C",
  "VTANR5L15V2600": "C",
  "VTANR5L15V2601": "C",
  "VTANR5L15V2602": "C",
  "VTANR5L15V2603": "C",
  "VTANR5L15V272": "P",
  "VTANR5L15V2733": "P",
  "VTANR5L15V2734": "P",
  "VTANR5L15V2735": "P",
  "VTANR5L15V2736": "P",
  "VTANR5L15V2737": "P",
  "VTANR5L15V2738": "P",
  "VTANR5L15V2739": "P",
  "VTANR5L15V2740": "P",
  "VTANR5L15V2741": "P",
  "VTANR5L15V2742": "P",
  "VTANR5L15V2743": "P",
  "VTANR5L15V2744": "P",
  "VTANR5L15V2745": "P",
  "VTANR5L15V2746": "P",
  "VTANR5L15V2747": "P",
  "VTANR5L15V2748": "P",
  "VTANR5L15V2749": "P",
  "VTANR5L15V2750": "P",
  "VTANR5L15V2751": "C",
  "VTANR5L15V2752": "C",
  "VTANR5L15V2753": "P",
  "VTANR5L15V2754": "P",
  "VTANR5L15V2755": "P",
  "VTANR5L15V2756": "P",
  "VTANR5L15V2757": "P",
  "VTANR5L15V2758": "P",
  "VTANR5L15V2759": "P",
  "VTANR5L15V2760": "C",
  "VTANR5L15V2761": "C",
  "VTANR5L15V2762": "C",
  "VTANR5L15V28": "C",
  "VTANR5L15V2803": "C",
  "VTANR5L15V2814": "P",
  "VTANR5L15V2815": "P",
  "VTANR5L15V2818": "C",
  "VTANR5L15V2819": "C",
  "VTANR5L15V2820": "C",
  "VTANR5L15V2821": "C",
  "VTANR5L15V2822": "P",
  "VTANR5L15V2823": "P",
  "VTANR5L15V2824": "P",
  "VTANR5L15V2825": "P",
  "VTANR5L15V2826": "P",
  "VTANR5L15V2831": "P",
  "VTANR5L15V2832": "C",
  "VTANR5L15V2833": "C",
  "VTANR5L15V2834": "P",
  "VTANR5L15V2835": "C",
  "VTANR5L15V2836": "C",
  "VTANR5L15V2842": "C",
  "VTANR5L15V2843": "C",
  "VTANR5L15V2844": "C",
  "VTANR5L15V2845": "C",
  "VTANR5L15V2846": "C",
  "VTANR5L15V2847": "C",
  "VTANR5L15V2848": "C",
  "VTANR5L15V2849": "P",
  "VTANR5L15V2882": "C",
  "VTANR5L15V2884": "C",
  "VTANR5L15V2887": "C",
  "VTANR5L15V2888": "A",
  "VTANR5L15V2889": "C",
  "VTANR5L15V2893": "C",
  "VTANR5L15V2894": "P",
  "VTANR5L15V2895": "C",
  "VTANR5L15V29": "C",
  "VTANR5L15V2916": "P",
  "VTANR5L15V2917": "C",
  "VTANR5L15V2918": "C",
  "VTANR5L15V2919": "P",
  "VTANR5L15V2920": "P",
  "VTANR5L15V2921": "C",
  "VTANR5L15V2922": "C",
  "VTANR5L15V2923": "P",
  "VTANR5L15V2924": "C",
  "VTANR5L15V2925": "P",
  "VTANR5L15V2926": "C",
  "VTANR5L15V2927": "P",
  "VTANR5L15V2928": "C",
  "VTANR5L15V2929": "P",
  "VTANR5L15V2930": "P",
  "VTANR5L15V2940": "A",
  "VTANR5L15V2941": "P",
  "VTANR5L15V2947": "C",
  "VTANR5L15V2948": "P",
  "VTANR5L15V2949": "P",
  "VTANR5L15V2950": "P",
  "VTANR5L15V2951": "P",
  "VTANR5L15V2952": "P",
  "VTANR5L15V2953": "C",
  "VTANR5L15V2954": "C",
  "VTANR5L15V2955": "P",
  "VTANR5L15V2972": "C",
  "VTANR5L15V2973": "C",
  "VTANR5L15V2974": "C",
  "VTANR5L15V2975": "C",
  "VTANR5L15V2976": "C",
  "VTANR5L15V2977": "C",
  "VTANR5L15V2978": "C",
  "VTANR5L15V2979": "C",
  "VTANR5L15V2980": "P",
  "VTANR5L15V2982": "C",
  "VTANR5L15V2983": "P",
  "VTANR5L15V2984": "C",
  "VTANR5L15V2991": "P",
  "VTANR5L15V2992": "C",
  "VTANR5L15V2996": "C",
  "VTANR5L15V2997": "C",
  "VTANR5L15V3": "C",
  "VTANR5L15V30": "P",
  "VTANR5L15V3006": "C",
  "VTANR5L15V3007": "C",
  "VTANR5L15V3008": "P",
  "VTANR5L15V3012": "C",
  "VTANR5L15V3013": "C",
  "VTANR5L15V305": "C",
  "VTANR5L15V3059": "P",
  "VTANR5L15V306": "C",
  "VTANR5L15V3060": "C",
  "VTANR5L15V3062": "P",
  "VTANR5L15V3063": "C",
  "VTANR5L15V3064": "C",
  "VTANR5L15V3065": "C",
  "VTANR5L15V3066": "P",
  "VTANR5L15V3067": "P",
  "VTANR5L15V3068": "C",
  "VTANR5L15V3069": "C",
  "VTANR5L15V307": "C",
  "VTANR5L15V3070": "C",
  "VTANR5L15V3071": "C",
  "VTANR5L15V3072": "C",
  "VTANR5L15V3073": "C",
  "VTANR5L15V3074": "C",
  "VTANR5L15V308": "C",
  "VTANR5L15V309": "C",
  "VTANR5L15V3094": "C",
  "VTANR5L15V3095": "C",
  "VTANR5L15V3096": "C",
  "VTANR5L15V3097": "C",
  "VTANR5L15V3098": "C",
  "VTANR5L15V3099": "C",
  "VTANR5L15V310": "P",
  "VTANR5L15V3100": "C",
  "VTANR5L15V3101": "C",
  "VTANR5L15V3102": "C",
  "VTANR5L15V3103": "C",
  "VTANR5L15V3104": "C",
  "VTANR5L15V3105": "C",
  "VTANR5L15V3106": "C",
  "VTANR5L15V3107": "C",
  "VTANR5L15V3108": "C",
  "VTANR5L15V3109": "P",
  "VTANR5L15V311": "C",
  "VTANR5L15V3110": "C",
  "VTANR5L15V3118": "C",
  "VTANR5L15V3119": "C",
  "VTANR5L15V3127": "P",
  "VTANR5L15V3128": "C",
  "VTANR5L15V3129": "C",
  "VTANR5L15V3130": "C",
  "VTANR5L15V314": "P",
  "VTANR5L15V3165": "C",
  "VTANR5L15V3166": "C",
  "VTANR5L15V3167": "P",
  "VTANR5L15V3168": "C",
  "VTANR5L15V3169": "C",
  "VTANR5L15V3170": "C",
  "VTANR5L15V3171": "C",
  "VTANR5L15V3172": "C",
  "VTANR5L15V3173": "C",
  "VTANR5L15V3174": "C",
  "VTANR5L15V3175": "C",
  "VTANR5L15V3176": "C",
  "VTANR5L15V3177": "P",
  "VTANR5L15V3178": "C",
  "VTANR5L15V3179": "C",
  "VTANR5L15V3180": "C",
  "VTANR5L15V3181": "P",
  "VTANR5L15V3182": "A",
  "VTANR5L15V3185": "C",
  "VTANR5L15V3186": "P",
  "VTANR5L15V3191": "P",
  "VTANR5L15V3192": "C",
  "VTANR5L15V3193": "P",
  "VTANR5L15V32": "C",
  "VTANR5L15V3202": "P",
  "VTANR5L15V3254": "P",
  "VTANR5L15V3279": "P",
  "VTANR5L15V3295": "P",
  "VTANR5L15V3308": "P",
  "VTANR5L15V3378": "P",
  "VTANR5L15V3379": "P",
  "VTANR5L15V3380": "C",
  "VTANR5L15V3381": "P",
  "VTANR5L15V3382": "P",
  "VTANR5L15V3383": "P",
  "VTANR5L15V3384": "C",
  "VTANR5L15V3386": "P",
  "VTANR5L15V3387": "P",
  "VTANR5L15V3388": "P",
  "VTANR5L15V3393": "P",
  "VTANR5L15V3394": "P",
  "VTANR5L15V3395": "C",
  "VTANR5L15V3397": "C",
  "VTANR5L15V3398": "P",
  "VTANR5L15V3399": "P",
  "VTANR5L15V3420": "P",
  "VTANR5L15V3421": "P",
  "VTANR5L15V3422": "P",
  "VTANR5L15V3423": "P",
  "VTANR5L15V3424": "P",
  "VTANR5L15V3425": "C",
  "VTANR5L15V3426": "P",
  "VTANR5L15V3432": "P",
  "VTANR5L15V3435": "C",
  "VTANR5L15V3436": "C",
  "VTANR5L15V3437": "C",
  "VTANR5L15V3438": "C",
  "VTANR5L15V3439": "C",
  "VTANR5L15V3440": "P",
  "VTANR5L15V3441": "P",
  "VTANR5L15V3442": "P",
  "VTANR5L15V3443": "P",
  "VTANR5L15V345": "P",
  "VTANR5L15V3454": "P",
  "VTANR5L15V3484": "P",
  "VTANR5L15V3486": "P",
  "VTANR5L15V3487": "P",
  "VTANR5L15V35": "C",
  "VTANR5L15V351": "P",
  "VTANR5L15V3511": "C",
  "VTANR5L15V3518": "P",
  "VTANR5L15V3522": "P",
  "VTANR5L15V3523": "C",
  "VTANR5L15V3524": "P",
  "VTANR5L15V3525": "P",
  "VTANR5L15V3526": "C",
  "VTANR5L15V3527": "P",
  "VTANR5L15V3528": "C",
  "VTANR5L15V3529": "P",
  "VTANR5L15V3530": "C",
  "VTANR5L15V3531": "P",
  "VTANR5L15V3532": "C",
  "VTANR5L15V3533": "P",
  "VTANR5L15V3535": "C",
  "VTANR5L15V3536": "C",
  "VTANR5L15V3537": "C",
  "VTANR5L15V3538": "P",
  "VTANR5L15V3539": "P",
  "VTANR5L15V3540": "P",
  "VTANR5L15V3541": "P",
  "VTANR5L15V3542": "P",
  "VTANR5L15V3543": "C",
  "VTANR5L15V3550": "C",
  "VTANR5L15V3551": "P",
  "VTANR5L15V3552": "C",
  "VTANR5L15V3553": "C",
  "VTANR5L15V3554": "P",
  "VTANR5L15V3555": "P",
  "VTANR5L15V3556": "P",
  "VTANR5L15V3557": "P",
  "VTANR5L15V3558": "P",
  "VTANR5L15V3559": "P",
  "VTANR5L15V3560": "P",
  "VTANR5L15V3562": "P",
  "VTANR5L15V3564": "C",
  "VTANR5L15V3565": "P",
  "VTANR5L15V3566": "P",
  "VTANR5L15V3570": "C",
  "VTANR5L15V3572": "P",
  "VTANR5L15V3573": "C",
  "VTANR5L15V3574": "C",
  "VTANR5L15V3575": "P",
  "VTANR5L15V3576": "P",
  "VTANR5L15V3577": "P",
  "VTANR5L15V3578": "C",
  "VTANR5L15V3579": "P",
  "VTANR5L15V3580": "P",
  "VTANR5L15V3581": "A",
  "VTANR5L15V3582": "P",
  "VTANR5L15V3583": "P",
  "VTANR5L15V3584": "P",
  "VTANR5L15V3585": "P",
  "VTANR5L15V3586": "P",
  "VTANR5L15V3587": "C",
  "VTANR5L15V3588": "C",
  "VTANR5L15V3589": "P",
  "VTANR5L15V3590": "P",
  "VTANR5L15V3591": "C",
  "VTANR5L15V3592": "P",
  "VTANR5L15V3593": "P",
  "VTANR5L15V3594": "C",
  "VTANR5L15V3595": "C",
  "VTANR5L15V3596": "P",
  "VTANR5L15V3597": "P",
  "VTANR5L15V3598": "P",
  "VTANR5L15V3599": "C",
  "VTANR5L15V36": "C",
  "VTANR5L15V3600": "C",
  "VTANR5L15V3601": "P",
  "VTANR5L15V3605": "P",
  "VTANR5L15V3606": "C",
  "VTANR5L15V3607": "P",
  "VTANR5L15V3608": "P",
  "VTANR5L15V3633": "P",
  "VTANR5L15V3642": "C",
  "VTANR5L15V3643": "P",
  "VTANR5L15V3644": "C",
  "VTANR5L15V3645": "C",
  "VTANR5L15V3646": "C",
  "VTANR5L15V3647": "P",
  "VTANR5L15V365": "P",
  "VTANR5L15V3664": "P",
  "VTANR5L15V3665": "C",
  "VTANR5L15V3666": "C",
  "VTANR5L15V3667": "C",
  "VTANR5L15V3668": "C",
  "VTANR5L15V3669": "C",
  "VTANR5L15V3670": "C",
  "VTANR5L15V3671": "C",
  "VTANR5L15V3672": "A",
  "VTANR5L15V3673": "P",
  "VTANR5L15V3674": "P",
  "VTANR5L15V3675": "C",
  "VTANR5L15V3676": "P",
  "VTANR5L15V3677": "P",
  "VTANR5L15V3678": "P",
  "VTANR5L15V3679": "P",
  "VTANR5L15V3680": "P",
  "VTANR5L15V3681": "C",
  "VTANR5L15V3682": "P",
  "VTANR5L15V3683": "P",
  "VTANR5L15V3684": "P",
  "VTANR5L15V3685": "P",
  "VTANR5L15V3686": "P",
  "VTANR5L15V3687": "C",
  "VTANR5L15V3688": "A",
  "VTANR5L15V3689": "A",
  "VTANR5L15V3690": "A",
  "VTANR5L15V3691": "A",
  "VTANR5L15V3692": "A",
  "VTANR5L15V3693": "P",
  "VTANR5L15V3694": "P",
  "VTANR5L15V3695": "C",
  "VTANR5L15V3696": "P",
  "VTANR5L15V3698": "P",
  "VTANR5L15V3699": "P",
  "VTANR5L15V37": "C",
  "VTANR5L15V3700": "C",
  "VTANR5L15V3701": "C",
  "VTANR5L15V3702": "P",
  "VTANR5L15V3703": "P",
  "VTANR5L15V3704": "C",
  "VTANR5L15V3705": "C",
  "VTANR5L15V3706": "C",
  "VTANR5L15V3707": "C",
  "VTANR5L15V3708": "P",
  "VTANR5L15V3709": "P",
  "VTANR5L15V38": "P",
  "VTANR5L15V39": "C",
  "VTANR5L15V4": "C",
  "VTANR5L15V40": "C",
  "VTANR5L15V407": "P",
  "VTANR5L15V408": "P",
  "VTANR5L15V41": "C",
  "VTANR5L15V419": "P",
  "VTANR5L15V42": "C",
  "VTANR5L15V43": "C",
  "VTANR5L15V433": "P",
  "VTANR5L15V44": "P",
  "VTANR5L15V447": "C",
  "VTANR5L15V448": "C",
  "VTANR5L15V449": "C",
  "VTANR5L15V45": "C",
  "VTANR5L15V450": "C",
  "VTANR5L15V451": "C",
  "VTANR5L15V452": "C",
  "VTANR5L15V453": "C",
  "VTANR5L15V454": "C",
  "VTANR5L15V455": "C",
  "VTANR5L15V456": "C",
  "VTANR5L15V457": "C",
  "VTANR5L15V458": "P",
  "VTANR5L15V459": "C",
  "VTANR5L15V46": "P",
  "VTANR5L15V460": "C",
  "VTANR5L15V461": "P",
  "VTANR5L15V462": "C",
  "VTANR5L15V463": "P",
  "VTANR5L15V464": "P",
  "VTANR5L15V465": "C",
  "VTANR5L15V466": "C",
  "VTANR5L15V467": "C",
  "VTANR5L15V468": "C",
  "VTANR5L15V469": "C",
  "VTANR5L15V47": "C",
  "VTANR5L15V470": "C",
  "VTANR5L15V471": "C",
  "VTANR5L15V472": "C",
  "VTANR5L15V473": "C",
  "VTANR5L15V474": "P",
  "VTANR5L15V477": "P",
  "VTANR5L15V48": "C",
  "VTANR5L15V483": "P",
  "VTANR5L15V49": "P",
  "VTANR5L15V5": "C",
  "VTANR5L15V50": "C",
  "VTANR5L15V51": "C",
  "VTANR5L15V53": "C",
  "VTANR5L15V54": "C",
  "VTANR5L15V55": "C",
  "VTANR5L15V56": "C",
  "VTANR5L15V586": "C",
  "VTANR5L15V587": "C",
  "VTANR5L15V588": "C",
  "VTANR5L15V589": "C",
  "VTANR5L15V590": "C",
  "VTANR5L15V591": "C",
  "VTANR5L15V592": "C",
  "VTANR5L15V593": "C",
  "VTANR5L15V594": "C",
  "VTANR5L15V595": "C",
  "VTANR5L15V6": "C",
  "VTANR5L15V629": "C",
  "VTANR5L15V630": "C",
  "VTANR5L15V631": "P",
  "VTANR5L15V632": "C",
  "VTANR5L15V633": "C",
  "VTANR5L15V634": "C",
  "VTANR5L15V635": "P",
  "VTANR5L15V637": "C",
  "VTANR5L15V7": "C",
  "VTANR5L15V716": "C",
  "VTANR5L15V717": "C",
  "VTANR5L15V718": "C",
  "VTANR5L15V720": "P",
  "VTANR5L15V721": "C",
  "VTANR5L15V722": "C",
  "VTANR5L15V723": "C",
  "VTANR5L15V729": "P",
  "VTANR5L15V73": "C",
  "VTANR5L15V74": "C",
  "VTANR5L15V75": "C",
  "VTANR5L15V752": "C",
  "VTANR5L15V753": "C",
  "VTANR5L15V754": "C",
  "VTANR5L15V755": "C",
  "VTANR5L15V76": "C",
  "VTANR5L15V762": "C",
  "VTANR5L15V763": "C",
  "VTANR5L15V764": "C",
  "VTANR5L15V765": "C",
  "VTANR5L15V766": "C",
  "VTANR5L15V767": "C",
  "VTANR5L15V768": "C",
  "VTANR5L15V769": "C",
  "VTANR5L15V77": "C",
  "VTANR5L15V770": "C",
  "VTANR5L15V771": "C",
  "VTANR5L15V772": "C",
  "VTANR5L15V773": "C",
  "VTANR5L15V774": "C",
  "VTANR5L15V775": "C",
  "VTANR5L15V776": "C",
  "VTANR5L15V777": "C",
  "VTANR5L15V778": "C",
  "VTANR5L15V779": "C",
  "VTANR5L15V78": "C",
  "VTANR5L15V780": "C",
  "VTANR5L15V781": "C",
  "VTANR5L15V782": "C",
  "VTANR5L15V783": "C",
  "VTANR5L15V784": "C",
  "VTANR5L15V785": "C",
  "VTANR5L15V786": "C",
  "VTANR5L15V787": "P",
  "VTANR5L15V788": "C",
  "VTANR5L15V789": "C",
  "VTANR5L15V79": "C",
  "VTANR5L15V790": "C",
  "VTANR5L15V791": "C",
  "VTANR5L15V792": "C",
  "VTANR5L15V793": "C",
  "VTANR5L15V794": "C",
  "VTANR5L15V795": "P",
  "VTANR5L15V798": "C",
  "VTANR5L15V799": "C",
  "VTANR5L15V8": "C",
  "VTANR5L15V800": "C",
  "VTANR5L15V801": "C",
  "VTANR5L15V802": "C",
  "VTANR5L15V816": "C",
  "VTANR5L15V817": "C",
  "VTANR5L15V818": "C",
  "VTANR5L15V819": "C",
  "VTANR5L15V820": "C",
  "VTANR5L15V821": "C",
  "VTANR5L15V822": "P",
  "VTANR5L15V823": "C",
  "VTANR5L15V835": "C",
  "VTANR5L15V836": "C",
  "VTANR5L15V837": "C",
  "VTANR5L15V838": "C",
  "VTANR5L15V9": "C",
  "VTANR5L15V928": "P",
  "VTANR5L15V942": "P",
  "VTANR5L15V974": "P",
  "VTANR5L15V982": "P",
  "VTANR5L15V983": "P",
  "VTANR5L15V985": "C",
  "VTANR5L15V986": "C",
  "VTANR5L15V987": "C",
  "VTANR5L15V988": "C",
  "VTANR5L15V989": "P",
  "VTANR5L15V990": "C"
 },
 "twitter": {
  "id": "15243103",
  "name": "Damien ADAM",
  "public_metrics": {
   "followers_count": 4110,
   "following_count": 595,
   "listed_count": 127,
   "tweet_count": 4877
  },
  "username": "damienadam76"
 },
 "twitter_username": {
  "status": "found",
  "value": "damienadam76"
 },
 "uid": "PA722038"
}