{
 "an_data_depute": {
  "dateNais": "1978-02-11",
  "femme": false,
  "ident": {
   "alpha": "Renson",
   "civ": "M.",
   "nom": "Renson",
   "prenom": "Hugues",
   "trigramme": "HRE"
  },
  "nom": "Hugues Renson"
 },
 "an_www_depute": {
  "groupe": "La République en Marche",
  "imgurl": "https://www2.assemblee-nationale.fr/static/tribun/15/photos/721824.jpg",
  "nosiege": "416"
 },
 "an_www_pic": {},
 "an_www_social": {
  "facebook_link": "https://fr-fr.facebook.com/HuguesRensonDepute/",
  "twitter_link": "https://twitter.com/@huguesrenson/"
 },
 "circo": {
  "acteurId": "OMC_PA721824",
  "civ": "M.",
  "communes": [
   "Paris",
   "Paris 15eme arrondissement (75015)"
  ],
  "departement": "Paris",
  "group": "La République en Marche",
  "nom": "Renson",
  "numCirco": "13",
  "numDepartement": "75",
  "prenom": "Hugues"
 },
 "datan": "https://datan.fr/deputes/paris-75/depute_hugues-renson",
 "lcdg": {
  "siege": {
   "curAngleIndex": 24,
   "curRadiusIndex": 3,
   "id": "ai24ri3",
   "no": 416,
   "polar": {
    "angle": 2.356194490192345,
    "radius": 0.5
   },
   "pos": {
    "x": -0.35355339059327373,
    "y": -0.3536232913905932
   }
  }
 },
 "nd_twitter": {
  "twitter": "huguesrenson",
  "url_an": "http://www2.assemblee-nationale.fr/deputes/fiche/OMC_PA721824"
 },
 "nosdeputes_link": "https://www.nosdeputes.fr/Hugues-Renson",
 "official_link": "https://www2.assemblee-nationale.fr/deputes/fiche/OMC_PA721824",
 "scrutins": {
  "VTANR5L15V1": "P",
  "VTANR5L15V10": "C",
  "VTANR5L15V1004": "C",
  "VTANR5L15V1005": "P",
  "VTANR5L15V1006": "P",
  "VTANR5L15V1008": "C",
  "VTANR5L15V1017": "N",
  "VTANR5L15V1018": "N",
  "VTANR5L15V1019": "N",
  "VTANR5L15V102": "C",
  "VTANR5L15V1020": "N",
  "VTANR5L15V103": "P",
  "VTANR5L15V1031": "C",
  "VTANR5L15V1032": "P",
  "VTANR5L15V104": "P",
  "VTANR5L15V105": "C",
  "VTANR5L15V106": "P",
  "VTANR5L15V1065": "C",
  "VTANR5L15V1066": "C",
  "VTANR5L15V1067": "C",
  "VTANR5L15V1068": "C",
  "VTANR5L15V1069": "C",
  "VTANR5L15V107": "P",
  "VTANR5L15V1075": "N",
  "VTANR5L15V1076": "N",
  "VTANR5L15V109": "C",
  "VTANR5L15V11": "C",
  "VTANR5L15V110": "C",
  "VTANR5L15V111": "C",
  "VTANR5L15V1119": "N",
  "VTANR5L15V112": "P",
  "VTANR5L15V113": "C",
  "VTANR5L15V114": "C",
  "VTANR5L15V115": "C",
  "VTANR5L15V1158": "N",
  "VTANR5L15V1159": "N",
  "VTANR5L15V116": "C",
  "VTANR5L15V117": "P",
  "VTANR5L15V1171": "P",
  "VTANR5L15V118": "C",
  "VTANR5L15V1188": "N",
  "VTANR5L15V1189": "N",
  "VTANR5L15V119": "P",
  "VTANR5L15V1190": "N",
  "VTANR5L15V1191": "N",
  "VTANR5L15V1192": "N",
  "VTANR5L15V12": "C",
  "VTANR5L15V120": "C",
  "VTANR5L15V1209": "P",
  "VTANR5L15V122": "N",
  "VTANR5L15V123": "N",
  "VTANR5L15V1236": "N",
  "VTANR5L15V1237": "N",
  "VTANR5L15V1238": "N",
  "VTANR5L15V1239": "N",
  "VTANR5L15V124": "N",
  "VTANR5L15V1240": "N",
  "VTANR5L15V1241": "N",
  "VTANR5L15V125": "C",
  "VTANR5L15V1250": "N",
  "VTANR5L15V1263": "P",
  "VTANR5L15V1264": "N",
  "VTANR5L15V1265": "N",
  "VTANR5L15V127": "N",
  "VTANR5L15V128": "N",
  "VTANR5L15V129": "N",
  "VTANR5L15V130": "C",
  "VTANR5L15V131": "C",
  "VTANR5L15V1312": "N",
  "VTANR5L15V1313": "N",
  "VTANR5L15V1314": "N",
  "VTANR5L15V1315": "N",
  "VTANR5L15V1316": "N",
  "VTANR5L15V1317": "N",
  "VTANR5L15V1318": "N",
  "VTANR5L15V1319": "N",
  "VTANR5L15V1320": "N",
  "VTANR5L15V1321": "N",
  "VTANR5L15V1322": "N",
  "VTANR5L15V1323": "N",
  "VTANR5L15V1324": "N",
  "VTANR5L15V1325": "N",
  "VTANR5L15V1326": "N",
  "VTANR5L15V1327": "N",
  "VTANR5L15V1328": "N",
  "VTANR5L15V1329": "N",
  "VTANR5L15V133": "C",
  "VTANR5L15V1330": "P",
  "VTANR5L15V134": "C",
  "VTANR5L15V138": "P",
  "VTANR5L15V1383": "N",
  "VTANR5L15V1384": "N",
  "VTANR5L15V1385": "N",
  "VTANR5L15V1386": "N",
  "VTANR5L15V1387": "N",
  "VTANR5L15V1388": "N",
  "VTANR5L15V1389": "N",
  "VTANR5L15V139": "P",
  "VTANR5L15V1415": "N",
  "VTANR5L15V1416": "N",
  "VTANR5L15V1417": "N",
  "VTANR5L15V1418": "N",
  "VTANR5L15V1429": "P",
  "VTANR5L15V1430": "C",
  "VTANR5L15V1432": "P",
  "VTANR5L15V1435": "N",
  "VTANR5L15V1436": "N",
  "VTANR5L15V1437": "N",
  "VTANR5L15V1438": "N",
  "VTANR5L15V145": "N",
  "VTANR5L15V146": "N",
  "VTANR5L15V1474": "N",
  "VTANR5L15V1475": "N",
  "VTANR5L15V1476": "N",
  "VTANR5L15V1477": "N",
  "VTANR5L15V1478": "N",
  "VTANR5L15V1479": "N",
  "VTANR5L15V1480": "N",
  "VTANR5L15V1481": "N",
  "VTANR5L15V1482": "N",
  "VTANR5L15V150": "C",
  "VTANR5L15V1500": "C",
  "VTANR5L15V151": "C",
  "VTANR5L15V1516": "N",
  "VTANR5L15V152": "C",
  "VTANR5L15V1527": "C",
  "VTANR5L15V1536": "P",
  "VTANR5L15V1537": "N",
  "VTANR5L15V1538": "N",
  "VTANR5L15V1539": "N",
  "VTANR5L15V156": "C",
  "VTANR5L15V157": "C",
  "VTANR5L15V1576": "N",
  "VTANR5L15V1577": "N",
  "VTANR5L15V1578": "N",
  "VTANR5L15V1579": "N",
  "VTANR5L15V158": "C",
  "VTANR5L15V1580": "N",
  "VTANR5L15V159": "C",
  "VTANR5L15V1596": "P",
  "VTANR5L15V1606": "C",
  "VTANR5L15V1608": "P",
  "VTANR5L15V1609": "C",
  "VTANR5L15V1610": "C",
  "VTANR5L15V1611": "P",
  "VTANR5L15V1612": "P",
  "VTANR5L15V1613": "P",
  "VTANR5L15V1614": "N",
  "VTANR5L15V1615": "N",
  "VTANR5L15V1620": "P",
  "VTANR5L15V1629": "N",
  "VTANR5L15V163": "N",
  "VTANR5L15V1633": "P",
  "VTANR5L15V1634": "P",
  "VTANR5L15V1635": "C",
  "VTANR5L15V1636": "N",
  "VTANR5L15V1637": "N",
  "VTANR5L15V1638": "N",
  "VTANR5L15V1639": "N",
  "VTANR5L15V164": "N",
  "VTANR5L15V1643": "N",
  "VTANR5L15V1644": "N",
  "VTANR5L15V165": "N",
  "VTANR5L15V166": "N",
  "VTANR5L15V1662": "A",
  "VTANR5L15V1671": "C",
  "VTANR5L15V1675": "N",
  "VTANR5L15V1676": "N",
  "VTANR5L15V1677": "N",
  "VTANR5L15V1678": "N",
  "VTANR5L15V1679": "N",
  "VTANR5L15V1680": "N",
  "VTANR5L15V1681": "N",
  "VTANR5L15V1682": "N",
  "VTANR5L15V1683": "N",
  "VTANR5L15V1684": "N",
  "VTANR5L15V1687": "N",
  "VTANR5L15V1688": "N",
  "VTANR5L15V1689": "N",
  "VTANR5L15V169": "P",
  "VTANR5L15V1690": "N",
  "VTANR5L15V1691": "N",
  "VTANR5L15V170": "P",
  "VTANR5L15V1709": "P",
  "VTANR5L15V171": "C",
  "VTANR5L15V1710": "P",
  "VTANR5L15V1711": "P",
  "VTANR5L15V1712": "N",
  "VTANR5L15V175": "N",
  "VTANR5L15V176": "N",
  "VTANR5L15V1767": "N",
  "VTANR5L15V1768": "N",
  "VTANR5L15V1769": "N",
  "VTANR5L15V1770": "N",
  "VTANR5L15V1771": "N",
  "VTANR5L15V1772": "N",
  "VTANR5L15V1778": "N",
  "VTANR5L15V1779": "N",
  "VTANR5L15V1780": "N",
  "VTANR5L15V1781": "N",
  "VTANR5L15V1782": "N",
  "VTANR5L15V1783": "N",
  "VTANR5L15V1784": "N",
  "VTANR5L15V1793": "N",
  "VTANR5L15V1794": "N",
  "VTANR5L15V1795": "N",
  "VTANR5L15V1796": "N",
  "VTANR5L15V1797": "N",
  "VTANR5L15V1798": "N",
  "VTANR5L15V18": "C",
  "VTANR5L15V1814": "P",
  "VTANR5L15V182": "P",
  "VTANR5L15V1821": "N",
  "VTANR5L15V1822": "N",
  "VTANR5L15V183": "P",
  "VTANR5L15V184": "P",
  "VTANR5L15V1840": "P",
  "VTANR5L15V1847": "N",
  "VTANR5L15V1848": "N",
  "VTANR5L15V1849": "N",
  "VTANR5L15V1850": "N",
  "VTANR5L15V1851": "N",
  "VTANR5L15V1852": "N",
  "VTANR5L15V1853": "N",
  "VTANR5L15V1865": "N",
  "VTANR5L15V1866": "N",
  "VTANR5L15V1867": "N",
  "VTANR5L15V1868": "N",
  "VTANR5L15V1869": "N",
  "VTANR5L15V1870": "N",
  "VTANR5L15V1871": "N",
  "VTANR5L15V1872": "N",
  "VTANR5L15V1873": "N",
  "VTANR5L15V1874": "N",
  "VTANR5L15V1892": "N",
  "VTANR5L15V1893": "N",
  "VTANR5L15V19": "C",
  "VTANR5L15V1903": "N",
  "VTANR5L15V1912": "P",
  "VTANR5L15V1917": "N",
  "VTANR5L15V1919": "N",
  "VTANR5L15V1920": "N",
  "VTANR5L15V1923": "P",
  "VTANR5L15V1926": "P",
  "VTANR5L15V1941": "P",
  "VTANR5L15V1942": "N",
  "VTANR5L15V1953": "N",
  "VTANR5L15V1954": "N",
  "VTANR5L15V1957": "P",
  "VTANR5L15V197": "P",
  "VTANR5L15V1988": "P",
  "VTANR5L15V1996": "N",
  "VTANR5L15V1997": "N",
  "VTANR5L15V1998": "N",
  "VTANR5L15V1999": "N",
  "VTANR5L15V2": "P",
  "VTANR5L15V20": "C",
  "VTANR5L15V2000": "N",
  "VTANR5L15V2015": "P",
  "VTANR5L15V2039": "P",
  "VTANR5L15V2045": "N",
  "VTANR5L15V2046": "N",
  "VTANR5L15V2047": "N",
  "VTANR5L15V2051": "C",
  "VTANR5L15V2052": "C",
  "VTANR5L15V2058": "P",
  "VTANR5L15V2059": "P",
  "VTANR5L15V206": "N",
  "VTANR5L15V2065": "P",
  "VTANR5L15V207": "N",
  "VTANR5L15V2070": "N",
  "VTANR5L15V2071": "P",
  "VTANR5L15V2078": "P",
  "VTANR5L15V2079": "P",
  "VTANR5L15V208": "P",
  "VTANR5L15V2080": "N",
  "VTANR5L15V2099": "N",
  "VTANR5L15V21": "C",
  "VTANR5L15V2100": "N",
  "VTANR5L15V2101": "N",
  "VTANR5L15V2102": "N",
  "VTANR5L15V2118": "N",
  "VTANR5L15V2119": "N",
  "VTANR5L15V2120": "N",
  "VTANR5L15V2121": "N",
  "VTANR5L15V2122": "N",
  "VTANR5L15V2123": "N",
  "VTANR5L15V2124": "N",
  "VTANR5L15V2125": "N",
  "VTANR5L15V2130": "P",
  "VTANR5L15V2131": "P",
  "VTANR5L15V2144": "N",
  "VTANR5L15V2145": "N",
  "VTANR5L15V2146": "P",
  "VTANR5L15V2147": "P",
  "VTANR5L15V2161": "N",
  "VTANR5L15V2162": "N",
  "VTANR5L15V2163": "N",
  "VTANR5L15V2166": "N",
  "VTANR5L15V2167": "N",
  "VTANR5L15V2168": "N",
  "VTANR5L15V2169": "N",
  "VTANR5L15V2171": "N",
  "VTANR5L15V2172": "N",
  "VTANR5L15V2173": "N",
  "VTANR5L15V2174": "N",
  "VTANR5L15V2175": "N",
  "VTANR5L15V2176": "N",
  "VTANR5L15V2177": "P",
  "VTANR5L15V22": "C",
  "VTANR5L15V2218": "N",
  "VTANR5L15V2219": "N",
  "VTANR5L15V2220": "N",
  "VTANR5L15V2221": "N",
  "VTANR5L15V2222": "N",
  "VTANR5L15V2223": "N",
  "VTANR5L15V2224": "N",
  "VTANR5L15V2225": "N",
  "VTANR5L15V2226": "N",
  "VTANR5L15V2227": "N",
  "VTANR5L15V2228": "N",
  "VTANR5L15V2229": "N",
  "VTANR5L15V2230": "N",
  "VTANR5L15V2235": "P",
  "VTANR5L15V226": "N",
  "VTANR5L15V227": "N",
  "VTANR5L15V23": "P",
  "VTANR5L15V2303": "C",
  "VTANR5L15V2305": "C",
  "VTANR5L15V2306": "N",
  "VTANR5L15V2307": "P",
  "VTANR5L15V2308": "P",
  "VTANR5L15V2311": "N",
  "VTANR5L15V2321": "N",
  "VTANR5L15V2322": "N",
  "VTANR5L15V2323": "N",
  "VTANR5L15V2324": "N",
  "VTANR5L15V2329": "P",
  "VTANR5L15V2335": "N",
  "VTANR5L15V2336": "P",
  "VTANR5L15V2337": "P",
  "VTANR5L15V2339": "N",
  "VTANR5L15V2340": "N",
  "VTANR5L15V2341": "N",
  "VTANR5L15V2342": "N",
  "VTANR5L15V2344": "N",
  "VTANR5L15V2345": "N",
  "VTANR5L15V2370": "N",
  "VTANR5L15V2371": "N",
  "VTANR5L15V2388": "P",
  "VTANR5L15V2389": "C",
  "VTANR5L15V2390": "C",
  "VTANR5L15V2391": "C",
  "VTANR5L15V2392": "C",
  "VTANR5L15V2393": "C",
  "VTANR5L15V2394": "C",
  "VTANR5L15V2395": "C",
  "VTANR5L15V2396": "C",
  "VTANR5L15V2397": "C",
  "VTANR5L15V2398": "C",
  "VTANR5L15V2399": "C",
  "VTANR5L15V2400": "C",
  "VTANR5L15V2401": "C",
  "VTANR5L15V2402": "P",
  "VTANR5L15V2404": "N",
  "VTANR5L15V2405": "N",
  "VTANR5L15V2406": "N",
  "VTANR5L15V2407": "P",
  "VTANR5L15V2413": "P",
  "VTANR5L15V2433": "N",
  "VTANR5L15V2434": "N",
  "VTANR5L15V2435": "N",
  "VTANR5L15V2436": "N",
  "VTANR5L15V2437": "N",
  "VTANR5L15V2438": "N",
  "VTANR5L15V2439": "N",
  "VTANR5L15V2440": "N",
  "VTANR5L15V2441": "N",
  "VTANR5L15V2442": "N",
  "VTANR5L15V2443": "N",
  "VTANR5L15V2444": "N",
  "VTANR5L15V2445": "N",
  "VTANR5L15V2446": "P",
  "VTANR5L15V25": "C",
  "VTANR5L15V2569": "C",
  "VTANR5L15V2570": "C",
  "VTANR5L15V2571": "C",
  "VTANR5L15V2572": "C",
  "VTANR5L15V2573": "C",
  "VTANR5L15V2574": "C",
  "VTANR5L15V2575": "C",
  "VTANR5L15V263": "N",
  "VTANR5L15V264": "N",
  "VTANR5L15V2642": "N",
  "VTANR5L15V2643": "N",
  "VTANR5L15V2644": "N",
  "VTANR5L15V2645": "N",
  "VTANR5L15V2646": "N",
  "VTANR5L15V2647": "N",
  "VTANR5L15V2648": "N",
  "VTANR5L15V2659": "C",
  "VTANR5L15V2673": "N",
  "VTANR5L15V2674": "N",
  "VTANR5L15V2675": "N",
  "VTANR5L15V2676": "N",
  "VTANR5L15V2677": "N",
  "VTANR5L15V2678": "N",
  "VTANR5L15V2708": "N",
  "VTANR5L15V2709": "N",
  "VTANR5L15V271": "P",
  "VTANR5L15V2710": "N",
  "VTANR5L15V2711": "N",
  "VTANR5L15V2712": "N",
  "VTANR5L15V2713": "N",
  "VTANR5L15V2714": "N",
  "VTANR5L15V2715": "N",
  "VTANR5L15V2716": "N",
  "VTANR5L15V2717": "N",
  "VTANR5L15V2718": "N",
  "VTANR5L15V272": "P",
  "VTANR5L15V2733": "P",
  "VTANR5L15V2734": "P",
  "VTANR5L15V2735": "P",
  "VTANR5L15V2736": "P",
  "VTANR5L15V2737": "P",
  "VTANR5L15V2738": "P",
  "VTANR5L15V2739": "P",
  "VTANR5L15V2740": "P",
  "VTANR5L15V2741": "P",
  "VTANR5L15V2742": "P",
  "VTANR5L15V2743": "P",
  "VTANR5L15V2744": "P",
  "VTANR5L15V2745": "P",
  "VTANR5L15V2746": "A",
  "VTANR5L15V2747": "P",
  "VTANR5L15V2748": "P",
  "VTANR5L15V2749": "P",
  "VTANR5L15V2750": "P",
  "VTANR5L15V2751": "C",
  "VTANR5L15V2752": "C",
  "VTANR5L15V2753": "P",
  "VTANR5L15V2754": "P",
  "VTANR5L15V2755": "P",
  "VTANR5L15V2756": "P",
  "VTANR5L15V2757": "P",
  "VTANR5L15V2758": "P",
  "VTANR5L15V2759": "P",
  "VTANR5L15V2760": "C",
  "VTANR5L15V2761": "C",
  "VTANR5L15V2762": "C",
  "VTANR5L15V2768": "N",
  "VTANR5L15V2769": "N",
  "VTANR5L15V2770": "N",
  "VTANR5L15V2789": "N",
  "VTANR5L15V2790": "N",
  "VTANR5L15V2791": "N",
  "VTANR5L15V2792": "N",
  "VTANR5L15V2793": "N",
  "VTANR5L15V2794": "N",
  "VTANR5L15V28": "N",
  "VTANR5L15V2800": "N",
  "VTANR5L15V2801": "N",
  "VTANR5L15V2802": "N",
  "VTANR5L15V2807": "N",
  "VTANR5L15V2808": "N",
  "VTANR5L15V2814": "P",
  "VTANR5L15V2816": "P",
  "VTANR5L15V2817": "P",
  "VTANR5L15V2857": "N",
  "VTANR5L15V2865": "P",
  "VTANR5L15V2866": "P",
  "VTANR5L15V2883": "N",
  "VTANR5L15V2884": "P",
  "VTANR5L15V2888": "N",
  "VTANR5L15V2889": "N",
  "VTANR5L15V2890": "N",
  "VTANR5L15V2891": "N",
  "VTANR5L15V2892": "N",
  "VTANR5L15V2893": "N",
  "VTANR5L15V2894": "N",
  "VTANR5L15V29": "N",
  "VTANR5L15V2930": "N",
  "VTANR5L15V2931": "N",
  "VTANR5L15V2932": "N",
  "VTANR5L15V2940": "P",
  "VTANR5L15V2941": "P",
  "VTANR5L15V2942": "N",
  "VTANR5L15V2944": "N",
  "VTANR5L15V2945": "N",
  "VTANR5L15V2946": "N",
  "VTANR5L15V2947": "N",
  "VTANR5L15V2948": "N",
  "VTANR5L15V2952": "P",
  "VTANR5L15V2970": "N",
  "VTANR5L15V2972": "N",
  "VTANR5L15V2973": "N",
  "VTANR5L15V2974": "N",
  "VTANR5L15V2975": "N",
  "VTANR5L15V2976": "N",
  "VTANR5L15V2977": "N",
  "VTANR5L15V2978": "N",
  "VTANR5L15V2979": "N",
  "VTANR5L15V2980": "N",
  "VTANR5L15V2981": "N",
  "VTANR5L15V2982": "N",
  "VTANR5L15V2983": "N",
  "VTANR5L15V2984": "N",
  "VTANR5L15V2991": "P",
  "VTANR5L15V2992": "C",
  "VTANR5L15V30": "N",
  "VTANR5L15V3006": "C",
  "VTANR5L15V3007": "C",
  "VTANR5L15V3008": "P",
  "VTANR5L15V3009": "C",
  "VTANR5L15V3010": "P",
  "VTANR5L15V3019": "C",
  "VTANR5L15V3020": "P",
  "VTANR5L15V3021": "P",
  "VTANR5L15V3059": "P",
  "VTANR5L15V3062": "N",
  "VTANR5L15V3063": "N",
  "VTANR5L15V3064": "N",
  "VTANR5L15V3065": "N",
  "VTANR5L15V3066": "P",
  "VTANR5L15V3075": "N",
  "VTANR5L15V3076": "N",
  "VTANR5L15V3077": "N",
  "VTANR5L15V3078": "N",
  "VTANR5L15V3079": "N",
  "VTANR5L15V3080": "N",
  "VTANR5L15V3081": "N",
  "VTANR5L15V3082": "N",
  "VTANR5L15V3083": "N",
  "VTANR5L15V3084": "N",
  "VTANR5L15V3085": "N",
  "VTANR5L15V3086": "N",
  "VTANR5L15V3087": "N",
  "VTANR5L15V3094": "C",
  "VTANR5L15V3095": "C",
  "VTANR5L15V3096": "C",
  "VTANR5L15V3097": "C",
  "VTANR5L15V3098": "C",
  "VTANR5L15V3099": "C",
  "VTANR5L15V31": "N",
  "VTANR5L15V3100": "C",
  "VTANR5L15V3101": "C",
  "VTANR5L15V3102": "C",
  "VTANR5L15V3103": "C",
  "VTANR5L15V3104": "C",
  "VTANR5L15V3105": "C",
  "VTANR5L15V3106": "C",
  "VTANR5L15V3107": "C",
  "VTANR5L15V3108": "C",
  "VTANR5L15V3109": "P",
  "VTANR5L15V3110": "C",
  "VTANR5L15V3112": "P",
  "VTANR5L15V3113": "P",
  "VTANR5L15V3114": "P",
  "VTANR5L15V3115": "C",
  "VTANR5L15V3116": "C",
  "VTANR5L15V3117": "P",
  "VTANR5L15V3124": "P",
  "VTANR5L15V3125": "P",
  "VTANR5L15V3126": "P",
  "VTANR5L15V3127": "N",
  "VTANR5L15V3128": "N",
  "VTANR5L15V3129": "N",
  "VTANR5L15V3130": "N",
  "VTANR5L15V314": "P",
  "VTANR5L15V3144": "C",
  "VTANR5L15V3179": "C",
  "VTANR5L15V3180": "C",
  "VTANR5L15V3186": "P",
  "VTANR5L15V3188": "P",
  "VTANR5L15V3189": "C",
  "VTANR5L15V3191": "P",
  "VTANR5L15V3194": "P",
  "VTANR5L15V3195": "P",
  "VTANR5L15V3196": "P",
  "VTANR5L15V3197": "P",
  "VTANR5L15V3198": "P",
  "VTANR5L15V3199": "P",
  "VTANR5L15V32": "C",
  "VTANR5L15V3200": "C",
  "VTANR5L15V3201": "P",
  "VTANR5L15V3202": "P",
  "VTANR5L15V3203": "P",
  "VTANR5L15V3204": "P",
  "VTANR5L15V3205": "C",
  "VTANR5L15V3206": "P",
  "VTANR5L15V321": "N",
  "VTANR5L15V3211": "C",
  "VTANR5L15V3212": "C",
  "VTANR5L15V323": "N",
  "VTANR5L15V3254": "A",
  "VTANR5L15V3255": "P",
  "VTANR5L15V3256": "P",
  "VTANR5L15V3257": "P",
  "VTANR5L15V3258": "P",
  "VTANR5L15V3259": "C",
  "VTANR5L15V3260": "C",
  "VTANR5L15V3272": "N",
  "VTANR5L15V3273": "N",
  "VTANR5L15V3274": "N",
  "VTANR5L15V3276": "P",
  "VTANR5L15V3277": "C",
  "VTANR5L15V3278": "P",
  "VTANR5L15V3279": "P",
  "VTANR5L15V3283": "N",
  "VTANR5L15V3295": "P",
  "VTANR5L15V3308": "P",
  "VTANR5L15V3315": "N",
  "VTANR5L15V3316": "N",
  "VTANR5L15V332": "N",
  "VTANR5L15V333": "N",
  "VTANR5L15V3350": "N",
  "VTANR5L15V3351": "N",
  "VTANR5L15V3352": "N",
  "VTANR5L15V3364": "N",
  "VTANR5L15V3378": "P",
  "VTANR5L15V338": "N",
  "VTANR5L15V3380": "C",
  "VTANR5L15V3381": "P",
  "VTANR5L15V3382": "P",
  "VTANR5L15V3383": "P",
  "VTANR5L15V3384": "C",
  "VTANR5L15V3385": "P",
  "VTANR5L15V3386": "P",
  "VTANR5L15V3387": "P",
  "VTANR5L15V3388": "P",
  "VTANR5L15V3389": "N",
  "VTANR5L15V3390": "N",
  "VTANR5L15V3391": "N",
  "VTANR5L15V3392": "N",
  "VTANR5L15V3393": "N",
  "VTANR5L15V3394": "N",
  "VTANR5L15V3399": "N",
  "VTANR5L15V3400": "N",
  "VTANR5L15V3401": "N",
  "VTANR5L15V3402": "N",
  "VTANR5L15V3403": "N",
  "VTANR5L15V342": "N",
  "VTANR5L15V3420": "N",
  "VTANR5L15V3421": "P",
  "VTANR5L15V3422": "P",
  "VTANR5L15V343": "N",
  "VTANR5L15V3435": "P",
  "VTANR5L15V3436": "P",
  "VTANR5L15V3437": "P",
  "VTANR5L15V3438": "P",
  "VTANR5L15V3439": "C",
  "VTANR5L15V344": "N",
  "VTANR5L15V3440": "P",
  "VTANR5L15V3447": "C",
  "VTANR5L15V3448": "P",
  "VTANR5L15V3449": "P",
  "VTANR5L15V345": "P",
  "VTANR5L15V3459": "N",
  "VTANR5L15V3460": "N",
  "VTANR5L15V3461": "N",
  "VTANR5L15V3479": "N",
  "VTANR5L15V3480": "N",
  "VTANR5L15V3481": "N",
  "VTANR5L15V3482": "N",
  "VTANR5L15V3483": "N",
  "VTANR5L15V3484": "P",
  "VTANR5L15V3488": "C",
  "VTANR5L15V3489": "P",
  "VTANR5L15V3490": "P",
  "VTANR5L15V3491": "P",
  "VTANR5L15V3492": "P",
  "VTANR5L15V3493": "P",
  "VTANR5L15V3494": "P",
  "VTANR5L15V3495": "C",
  "VTANR5L15V3496": "P",
  "VTANR5L15V3497": "C",
  "VTANR5L15V3498": "P",
  "VTANR5L15V3499": "P",
  "VTANR5L15V35": "C",
  "VTANR5L15V3500": "P",
  "VTANR5L15V3501": "C",
  "VTANR5L15V351": "P",
  "VTANR5L15V3511": "C",
  "VTANR5L15V3512": "N",
  "VTANR5L15V3513": "N",
  "VTANR5L15V3518": "P",
  "VTANR5L15V3522": "N",
  "VTANR5L15V3523": "N",
  "VTANR5L15V3524": "N",
  "VTANR5L15V3525": "N",
  "VTANR5L15V3526": "N",
  "VTANR5L15V3527": "N",
  "VTANR5L15V3535": "N",
  "VTANR5L15V3536": "N",
  "VTANR5L15V3537": "N",
  "VTANR5L15V3544": "N",
  "VTANR5L15V3545": "N",
  "VTANR5L15V3546": "N",
  "VTANR5L15V3547": "N",
  "VTANR5L15V3548": "N",
  "VTANR5L15V3549": "N",
  "VTANR5L15V3567": "P",
  "VTANR5L15V3568": "N",
  "VTANR5L15V3571": "P",
  "VTANR5L15V358": "P",
  "VTANR5L15V36": "C",
  "VTANR5L15V360": "P",
  "VTANR5L15V363": "N",
  "VTANR5L15V3633": "P",
  "VTANR5L15V364": "N",
  "VTANR5L15V3641": "N",
  "VTANR5L15V3642": "N",
  "VTANR5L15V3643": "N",
  "VTANR5L15V3644": "N",
  "VTANR5L15V3645": "N",
  "VTANR5L15V3646": "N",
  "VTANR5L15V3647": "N",
  "VTANR5L15V365": "P",
  "VTANR5L15V3738": "P",
  "VTANR5L15V3751": "N",
  "VTANR5L15V3752": "N",
  "VTANR5L15V3753": "N",
  "VTANR5L15V3754": "N",
  "VTANR5L15V3755": "N",
  "VTANR5L15V3756": "P",
  "VTANR5L15V3757": "P",
  "VTANR5L15V3758": "C",
  "VTANR5L15V3759": "P",
  "VTANR5L15V3760": "P",
  "VTANR5L15V3761": "P",
  "VTANR5L15V3762": "N",
  "VTANR5L15V3763": "N",
  "VTANR5L15V3778": "P",
  "VTANR5L15V3779": "P",
  "VTANR5L15V3780": "P",
  "VTANR5L15V380": "P",
  "VTANR5L15V382": "P",
  "VTANR5L15V383": "P",
  "VTANR5L15V385": "N",
  "VTANR5L15V386": "N",
  "VTANR5L15V389": "P",
  "VTANR5L15V39": "C",
  "VTANR5L15V4": "C",
  "VTANR5L15V407": "P",
  "VTANR5L15V416": "P",
  "VTANR5L15V419": "P",
  "VTANR5L15V420": "N",
  "VTANR5L15V433": "P",
  "VTANR5L15V434": "N",
  "VTANR5L15V441": "P",
  "VTANR5L15V447": "N",
  "VTANR5L15V448": "N",
  "VTANR5L15V459": "N",
  "VTANR5L15V460": "N",
  "VTANR5L15V461": "N",
  "VTANR5L15V462": "N",
  "VTANR5L15V463": "N",
  "VTANR5L15V464": "N",
  "VTANR5L15V47": "C",
  "VTANR5L15V474": "N",
  "VTANR5L15V475": "C",
  "VTANR5L15V477": "P",
  "VTANR5L15V48": "C",
  "VTANR5L15V483": "P",
  "VTANR5L15V489": "C",
  "VTANR5L15V49": "P",
  "VTANR5L15V490": "C",
  "VTANR5L15V491": "P",
  "VTANR5L15V492": "C",
  "VTANR5L15V493": "C",
  "VTANR5L15V495": "C",
  "VTANR5L15V5": "C",
  "VTANR5L15V50": "N",
  "VTANR5L15V503": "N",
  "VTANR5L15V504": "N",
  "VTANR5L15V505": "N",
  "VTANR5L15V506": "N",
  "VTANR5L15V507": "N",
  "VTANR5L15V508": "N",
  "VTANR5L15V509": "N",
  "VTANR5L15V51": "N",
  "VTANR5L15V510": "N",
  "VTANR5L15V511": "N",
  "VTANR5L15V512": "N",
  "VTANR5L15V513": "N",
  "VTANR5L15V514": "N",
  "VTANR5L15V518": "N",
  "VTANR5L15V519": "N",
  "VTANR5L15V520": "N",
  "VTANR5L15V521": "N",
  "VTANR5L15V522": "N",
  "VTANR5L15V523": "N",
  "VTANR5L15V524": "N",
  "VTANR5L15V525": "N",
  "VTANR5L15V526": "N",
  "VTANR5L15V527": "N",
  "VTANR5L15V528": "N",
  "VTANR5L15V529": "N",
  "VTANR5L15V53": "C",
  "VTANR5L15V530": "N",
  "VTANR5L15V531": "N",
  "VTANR5L15V532": "N",
  "VTANR5L15V533": "N",
  "VTANR5L15V534": "N",
  "VTANR5L15V535": "N",
  "VTANR5L15V536": "N",
  "VTANR5L15V537": "N",
  "VTANR5L15V538": "N",
  "VTANR5L15V539": "N",
  "VTANR5L15V54": "C",
  "VTANR5L15V540": "N",
  "VTANR5L15V541": "N",
  "VTANR5L15V55": "C",
  "VTANR5L15V567": "C",
  "VTANR5L15V572": "C",
  "VTANR5L15V573": "C",
  "VTANR5L15V574": "C",
  "VTANR5L15V575": "C",
  "VTANR5L15V578": "P",
  "VTANR5L15V579": "P",
  "VTANR5L15V6": "C",
  "VTANR5L15V64": "P",
  "VTANR5L15V646": "N",
  "VTANR5L15V647": "N",
  "VTANR5L15V648": "N",
  "VTANR5L15V649": "N",
  "VTANR5L15V65": "C",
  "VTANR5L15V66": "C",
  "VTANR5L15V668": "N",
  "VTANR5L15V669": "N",
  "VTANR5L15V67": "C",
  "VTANR5L15V670": "N",
  "VTANR5L15V671": "N",
  "VTANR5L15V672": "N",
  "VTANR5L15V693": "C",
  "VTANR5L15V694": "C",
  "VTANR5L15V695": "C",
  "VTANR5L15V696": "P",
  "VTANR5L15V697": "C",
  "VTANR5L15V7": "C",
  "VTANR5L15V70": "C",
  "VTANR5L15V714": "N",
  "VTANR5L15V715": "N",
  "VTANR5L15V716": "N",
  "VTANR5L15V717": "N",
  "VTANR5L15V718": "N",
  "VTANR5L15V729": "P",
  "VTANR5L15V733": "N",
  "VTANR5L15V734": "N",
  "VTANR5L15V735": "N",
  "VTANR5L15V736": "N",
  "VTANR5L15V737": "N",
  "VTANR5L15V738": "N",
  "VTANR5L15V74": "C",
  "VTANR5L15V748": "N",
  "VTANR5L15V749": "N",
  "VTANR5L15V75": "C",
  "VTANR5L15V750": "N",
  "VTANR5L15V752": "N",
  "VTANR5L15V753": "N",
  "VTANR5L15V754": "N",
  "VTANR5L15V755": "N",
  "VTANR5L15V756": "N",
  "VTANR5L15V757": "N",
  "VTANR5L15V758": "N",
  "VTANR5L15V759": "N",
  "VTANR5L15V76": "C",
  "VTANR5L15V8": "C",
  "VTANR5L15V807": "N",
  "VTANR5L15V808": "N",
  "VTANR5L15V809": "N",
  "VTANR5L15V81": "C",
  "VTANR5L15V810": "N",
  "VTANR5L15V811": "N",
  "VTANR5L15V82": "N",
  "VTANR5L15V83": "N",
  "VTANR5L15V84": "N",
  "VTANR5L15V840": "C",
  "VTANR5L15V841": "C",
  "VTANR5L15V852": "N",
  "VTANR5L15V853": "N",
  "VTANR5L15V9": "C",
  "VTANR5L15V92": "N",
  "VTANR5L15V928": "P",
  "VTANR5L15V929": "N",
  "VTANR5L15V93": "N",
  "VTANR5L15V930": "N",
  "VTANR5L15V931": "N",
  "VTANR5L15V932": "N",
  "VTANR5L15V933": "N",
  "VTANR5L15V934": "N",
  "VTANR5L15V94": "N",
  "VTANR5L15V941": "C",
  "VTANR5L15V942": "P",
  "VTANR5L15V949": "N",
  "VTANR5L15V950": "N",
  "VTANR5L15V958": "C",
  "VTANR5L15V974": "P",
  "VTANR5L15V979": "N",
  "VTANR5L15V980": "N",
  "VTANR5L15V981": "N",
  "VTANR5L15V982": "N",
  "VTANR5L15V990": "N",
  "VTANR5L15V991": "C",
  "VTANR5L15V993": "P",
  "VTANR5L15V994": "C",
  "VTANR5L15V995": "P"
 },
 "twitter": {
  "id": "705617755",
  "name": "Hugues Renson",
  "public_metrics": {
   "followers_count": 21020,
   "following_count": 1993,
   "listed_count": 249,
   "tweet_count": 4662
  },
  "username": "huguesrenson"
 },
 "twitter_username": {
  "status": "found",
  "value": "huguesrenson"
 },
 "uid": "PA721824"
}