{
 "an_data_depute": {
  "dateNais": "1975-08-12",
  "femme": false,
  "ident": {
   "alpha": "Arend",
   "civ": "M.",
   "nom": "Arend",
   "prenom": "Christophe",
   "trigramme": "CAR"
  },
  "nom": "Christophe Arend"
 },
 "an_www_depute": {
  "groupe": "La République en Marche",
  "imgurl": "https://www2.assemblee-nationale.fr/static/tribun/15/photos/720310.jpg",
  "nosiege": "514"
 },
 "an_www_pic": {},
 "an_www_social": {},
 "circo": {
  "acteurId": "OMC_PA720310",
  "civ": "M.",
  "communes": [
   "Alsting (57515)",
   "Barst (57450)",
   "Behren-lès-Forbach (57460)",
   "Betting (57800)",
   "Bousbach (57460)",
   "Béning-lès-Saint-Avold (57800)",
   "Cappel (57450)",
   "Cocheren (57800)",
   "Diebling (57980)",
   "Etzling (57460)",
   "Farschviller (57450)",
   "Farébersviller (57450)",
   "Folkling (57600)",
   "Forbach (57600)",
   "Freyming-Merlebach (57800)",
   "Guenviller (57470)",
   "Henriville (57450)",
   "Hoste (57510)",
   "Kerbach (57460)",
   "Metzing (57980)",
   "Morsbach (57600)",
   "Nousseviller-Saint-Nabor (57990)",
   "OEting (57600)",
   "Petite-Rosselle (57540)",
   "Rosbruck (57800)",
   "Schoeneck (57350)",
   "Seingbouse (57455)",
   "Spicheren (57350)",
   "Stiring-Wendel (57350)",
   "Tenteling (57980)",
   "Théding (57450)"
  ],
  "departement": "Moselle",
  "group": "La République en Marche",
  "nom": "Arend",
  "numCirco": "6",
  "numDepartement": "57",
  "prenom": "Christophe"
 },
 "datan": "https://datan.fr/deputes/moselle-57/depute_christophe-arend",
 "lcdg": {
  "siege": {
   "curAngleIndex": 41,
   "curRadiusIndex": 6,
   "id": "ai41ri6",
   "no": 514,
   "polar": {
    "angle": 2.430288656550595,
    "radius": 0.6875
   },
   "pos": {
    "x": -0.5207889789861139,
    "y": -0.4489039412012593
   }
  }
 },
 "nd_twitter": {
  "twitter": "christophearend",
  "url_an": "http://www2.assemblee-nationale.fr/deputes/fiche/OMC_PA720310"
 },
 "nosdeputes_link": "https://www.nosdeputes.fr/Christophe-Arend",
 "official_link": "https://www2.assemblee-nationale.fr/deputes/fiche/OMC_PA720310",
 "scrutins": {
  "VTANR5L15V1": "P",
  "VTANR5L15V1008": "C",
  "VTANR5L15V1009": "C",
  "VTANR5L15V1010": "C",
  "VTANR5L15V1011": "C",
  "VTANR5L15V1012": "C",
  "VTANR5L15V1013": "C",
  "VTANR5L15V1014": "C",
  "VTANR5L15V1015": "C",
  "VTANR5L15V1016": "C",
  "VTANR5L15V1017": "C",
  "VTANR5L15V1018": "C",
  "VTANR5L15V1019": "C",
  "VTANR5L15V1020": "C",
  "VTANR5L15V1021": "C",
  "VTANR5L15V1022": "C",
  "VTANR5L15V1023": "C",
  "VTANR5L15V1024": "C",
  "VTANR5L15V1025": "C",
  "VTANR5L15V1026": "C",
  "VTANR5L15V106": "P",
  "VTANR5L15V107": "P",
  "VTANR5L15V1171": "P",
  "VTANR5L15V118": "C",
  "VTANR5L15V1181": "P",
  "VTANR5L15V119": "P",
  "VTANR5L15V1209": "P",
  "VTANR5L15V1230": "C",
  "VTANR5L15V1231": "C",
  "VTANR5L15V1232": "C",
  "VTANR5L15V1233": "C",
  "VTANR5L15V1234": "C",
  "VTANR5L15V1235": "C",
  "VTANR5L15V1236": "P",
  "VTANR5L15V1237": "C",
  "VTANR5L15V1238": "C",
  "VTANR5L15V125": "C",
  "VTANR5L15V1263": "P",
  "VTANR5L15V1330": "P",
  "VTANR5L15V1341": "C",
  "VTANR5L15V1342": "C",
  "VTANR5L15V1343": "C",
  "VTANR5L15V1344": "C",
  "VTANR5L15V1345": "C",
  "VTANR5L15V138": "P",
  "VTANR5L15V139": "P",
  "VTANR5L15V1390": "C",
  "VTANR5L15V1391": "C",
  "VTANR5L15V1392": "C",
  "VTANR5L15V1393": "C",
  "VTANR5L15V1394": "C",
  "VTANR5L15V1395": "C",
  "VTANR5L15V1396": "C",
  "VTANR5L15V1397": "C",
  "VTANR5L15V1398": "C",
  "VTANR5L15V1399": "C",
  "VTANR5L15V1400": "P",
  "VTANR5L15V1429": "P",
  "VTANR5L15V1430": "C",
  "VTANR5L15V1431": "P",
  "VTANR5L15V1432": "P",
  "VTANR5L15V145": "C",
  "VTANR5L15V146": "C",
  "VTANR5L15V1489": "P",
  "VTANR5L15V1490": "P",
  "VTANR5L15V1491": "C",
  "VTANR5L15V1492": "P",
  "VTANR5L15V1500": "C",
  "VTANR5L15V1534": "C",
  "VTANR5L15V1536": "P",
  "VTANR5L15V1557": "P",
  "VTANR5L15V1558": "C",
  "VTANR5L15V1559": "C",
  "VTANR5L15V1560": "C",
  "VTANR5L15V1561": "C",
  "VTANR5L15V1562": "C",
  "VTANR5L15V1563": "C",
  "VTANR5L15V1564": "C",
  "VTANR5L15V1565": "C",
  "VTANR5L15V1566": "C",
  "VTANR5L15V1614": "C",
  "VTANR5L15V1633": "P",
  "VTANR5L15V1634": "P",
  "VTANR5L15V1643": "P",
  "VTANR5L15V1662": "P",
  "VTANR5L15V1709": "P",
  "VTANR5L15V1711": "P",
  "VTANR5L15V18": "C",
  "VTANR5L15V1814": "P",
  "VTANR5L15V1817": "C",
  "VTANR5L15V183": "P",
  "VTANR5L15V1837": "C",
  "VTANR5L15V1839": "P",
  "VTANR5L15V184": "P",
  "VTANR5L15V1840": "P",
  "VTANR5L15V19": "C",
  "VTANR5L15V1912": "P",
  "VTANR5L15V1926": "P",
  "VTANR5L15V1928": "P",
  "VTANR5L15V1941": "P",
  "VTANR5L15V1958": "C",
  "VTANR5L15V196": "C",
  "VTANR5L15V198": "P",
  "VTANR5L15V1986": "P",
  "VTANR5L15V1987": "C",
  "VTANR5L15V1988": "P",
  "VTANR5L15V1989": "C",
  "VTANR5L15V1990": "C",
  "VTANR5L15V1991": "C",
  "VTANR5L15V1994": "P",
  "VTANR5L15V1998": "P",
  "VTANR5L15V1999": "P",
  "VTANR5L15V20": "C",
  "VTANR5L15V2000": "C",
  "VTANR5L15V2014": "C",
  "VTANR5L15V2018": "C",
  "VTANR5L15V2039": "P",
  "VTANR5L15V2059": "P",
  "VTANR5L15V2071": "P",
  "VTANR5L15V2078": "P",
  "VTANR5L15V2079": "P",
  "VTANR5L15V208": "P",
  "VTANR5L15V21": "C",
  "VTANR5L15V2130": "P",
  "VTANR5L15V2131": "P",
  "VTANR5L15V2146": "A",
  "VTANR5L15V2147": "P",
  "VTANR5L15V2149": "P",
  "VTANR5L15V2177": "P",
  "VTANR5L15V22": "C",
  "VTANR5L15V2235": "P",
  "VTANR5L15V23": "P",
  "VTANR5L15V2307": "P",
  "VTANR5L15V2308": "P",
  "VTANR5L15V2329": "P",
  "VTANR5L15V2337": "P",
  "VTANR5L15V2338": "P",
  "VTANR5L15V24": "C",
  "VTANR5L15V25": "C",
  "VTANR5L15V2642": "C",
  "VTANR5L15V2643": "C",
  "VTANR5L15V2644": "C",
  "VTANR5L15V2645": "C",
  "VTANR5L15V2646": "C",
  "VTANR5L15V2647": "C",
  "VTANR5L15V2648": "C",
  "VTANR5L15V272": "P",
  "VTANR5L15V2733": "P",
  "VTANR5L15V2734": "P",
  "VTANR5L15V2735": "P",
  "VTANR5L15V2736": "P",
  "VTANR5L15V2737": "P",
  "VTANR5L15V2738": "P",
  "VTANR5L15V2739": "P",
  "VTANR5L15V2740": "P",
  "VTANR5L15V2741": "P",
  "VTANR5L15V2742": "P",
  "VTANR5L15V2743": "P",
  "VTANR5L15V2744": "P",
  "VTANR5L15V2745": "P",
  "VTANR5L15V2746": "P",
  "VTANR5L15V2747": "P",
  "VTANR5L15V2748": "P",
  "VTANR5L15V2749": "P",
  "VTANR5L15V2750": "P",
  "VTANR5L15V2751": "C",
  "VTANR5L15V2752": "C",
  "VTANR5L15V2753": "P",
  "VTANR5L15V2754": "P",
  "VTANR5L15V2755": "P",
  "VTANR5L15V2756": "P",
  "VTANR5L15V2757": "P",
  "VTANR5L15V2758": "P",
  "VTANR5L15V2759": "P",
  "VTANR5L15V2760": "C",
  "VTANR5L15V2761": "C",
  "VTANR5L15V2762": "C",
  "VTANR5L15V28": "C",
  "VTANR5L15V2814": "P",
  "VTANR5L15V2816": "P",
  "VTANR5L15V2867": "C",
  "VTANR5L15V29": "C",
  "VTANR5L15V2940": "P",
  "VTANR5L15V2941": "P",
  "VTANR5L15V2991": "P",
  "VTANR5L15V3059": "P",
  "VTANR5L15V3061": "P",
  "VTANR5L15V3066": "P",
  "VTANR5L15V3094": "C",
  "VTANR5L15V3095": "C",
  "VTANR5L15V3096": "C",
  "VTANR5L15V3097": "C",
  "VTANR5L15V3098": "C",
  "VTANR5L15V3099": "C",
  "VTANR5L15V3100": "C",
  "VTANR5L15V3101": "C",
  "VTANR5L15V3102": "C",
  "VTANR5L15V3103": "C",
  "VTANR5L15V3104": "C",
  "VTANR5L15V3105": "C",
  "VTANR5L15V3106": "C",
  "VTANR5L15V3107": "C",
  "VTANR5L15V3108": "C",
  "VTANR5L15V3109": "P",
  "VTANR5L15V3110": "C",
  "VTANR5L15V3111": "C",
  "VTANR5L15V3112": "P",
  "VTANR5L15V3127": "P",
  "VTANR5L15V3128": "C",
  "VTANR5L15V3129": "C",
  "VTANR5L15V3130": "C",
  "VTANR5L15V3135": "P",
  "VTANR5L15V314": "P",
  "VTANR5L15V3145": "C",
  "VTANR5L15V3146": "C",
  "VTANR5L15V3147": "C",
  "VTANR5L15V3148": "C",
  "VTANR5L15V3149": "C",
  "VTANR5L15V3150": "C",
  "VTANR5L15V3186": "P",
  "VTANR5L15V3187": "C",
  "VTANR5L15V3188": "P",
  "VTANR5L15V3254": "P",
  "VTANR5L15V3255": "P",
  "VTANR5L15V3256": "P",
  "VTANR5L15V3257": "P",
  "VTANR5L15V3258": "P",
  "VTANR5L15V3259": "C",
  "VTANR5L15V3260": "C",
  "VTANR5L15V329": "C",
  "VTANR5L15V3295": "P",
  "VTANR5L15V3297": "P",
  "VTANR5L15V330": "C",
  "VTANR5L15V3300": "P",
  "VTANR5L15V3301": "C",
  "VTANR5L15V3303": "A",
  "VTANR5L15V3304": "P",
  "VTANR5L15V3305": "P",
  "VTANR5L15V3308": "P",
  "VTANR5L15V3311": "P",
  "VTANR5L15V3312": "C",
  "VTANR5L15V3313": "C",
  "VTANR5L15V3314": "P",
  "VTANR5L15V3378": "P",
  "VTANR5L15V339": "P",
  "VTANR5L15V3421": "P",
  "VTANR5L15V3422": "P",
  "VTANR5L15V3454": "P",
  "VTANR5L15V3455": "P",
  "VTANR5L15V3457": "C",
  "VTANR5L15V3458": "C",
  "VTANR5L15V3459": "C",
  "VTANR5L15V3460": "C",
  "VTANR5L15V3464": "C",
  "VTANR5L15V3465": "C",
  "VTANR5L15V3468": "C",
  "VTANR5L15V3469": "C",
  "VTANR5L15V3470": "C",
  "VTANR5L15V3471": "C",
  "VTANR5L15V3472": "C",
  "VTANR5L15V3473": "C",
  "VTANR5L15V3474": "C",
  "VTANR5L15V3475": "C",
  "VTANR5L15V3476": "C",
  "VTANR5L15V3484": "P",
  "VTANR5L15V3485": "P",
  "VTANR5L15V3508": "P",
  "VTANR5L15V3509": "P",
  "VTANR5L15V351": "P",
  "VTANR5L15V3513": "P",
  "VTANR5L15V3518": "P",
  "VTANR5L15V3550": "A",
  "VTANR5L15V3551": "P",
  "VTANR5L15V3554": "P",
  "VTANR5L15V3555": "P",
  "VTANR5L15V3556": "P",
  "VTANR5L15V3557": "P",
  "VTANR5L15V3558": "P",
  "VTANR5L15V3559": "P",
  "VTANR5L15V3560": "P",
  "VTANR5L15V3562": "P",
  "VTANR5L15V3563": "C",
  "VTANR5L15V3564": "C",
  "VTANR5L15V3565": "P",
  "VTANR5L15V3566": "P",
  "VTANR5L15V3569": "P",
  "VTANR5L15V3570": "C",
  "VTANR5L15V3571": "P",
  "VTANR5L15V3591": "C",
  "VTANR5L15V3592": "P",
  "VTANR5L15V3593": "P",
  "VTANR5L15V3594": "C",
  "VTANR5L15V3595": "C",
  "VTANR5L15V3596": "P",
  "VTANR5L15V3597": "P",
  "VTANR5L15V3598": "P",
  "VTANR5L15V3599": "C",
  "VTANR5L15V360": "P",
  "VTANR5L15V3600": "C",
  "VTANR5L15V3601": "P",
  "VTANR5L15V3605": "P",
  "VTANR5L15V3606": "C",
  "VTANR5L15V3607": "P",
  "VTANR5L15V3608": "P",
  "VTANR5L15V3633": "P",
  "VTANR5L15V365": "P",
  "VTANR5L15V3720": "C",
  "VTANR5L15V3721": "C",
  "VTANR5L15V3722": "C",
  "VTANR5L15V3723": "C",
  "VTANR5L15V3724": "C",
  "VTANR5L15V3725": "C",
  "VTANR5L15V3726": "P",
  "VTANR5L15V3727": "P",
  "VTANR5L15V3728": "C",
  "VTANR5L15V3729": "C",
  "VTANR5L15V3730": "P",
  "VTANR5L15V3731": "C",
  "VTANR5L15V3732": "C",
  "VTANR5L15V3733": "P",
  "VTANR5L15V3734": "C",
  "VTANR5L15V3738": "P",
  "VTANR5L15V3751": "C",
  "VTANR5L15V3754": "P",
  "VTANR5L15V389": "P",
  "VTANR5L15V390": "C",
  "VTANR5L15V391": "C",
  "VTANR5L15V392": "C",
  "VTANR5L15V407": "P",
  "VTANR5L15V408": "P",
  "VTANR5L15V419": "P",
  "VTANR5L15V433": "P",
  "VTANR5L15V447": "C",
  "VTANR5L15V448": "C",
  "VTANR5L15V449": "C",
  "VTANR5L15V450": "C",
  "VTANR5L15V451": "C",
  "VTANR5L15V452": "C",
  "VTANR5L15V453": "C",
  "VTANR5L15V454": "C",
  "VTANR5L15V455": "C",
  "VTANR5L15V456": "C",
  "VTANR5L15V457": "C",
  "VTANR5L15V458": "P",
  "VTANR5L15V459": "C",
  "VTANR5L15V460": "C",
  "VTANR5L15V461": "P",
  "VTANR5L15V462": "C",
  "VTANR5L15V463": "P",
  "VTANR5L15V467": "C",
  "VTANR5L15V471": "C",
  "VTANR5L15V472": "C",
  "VTANR5L15V473": "C",
  "VTANR5L15V477": "P",
  "VTANR5L15V478": "C",
  "VTANR5L15V49": "P",
  "VTANR5L15V50": "C",
  "VTANR5L15V57": "C",
  "VTANR5L15V58": "C",
  "VTANR5L15V581": "C",
  "VTANR5L15V582": "C",
  "VTANR5L15V583": "C",
  "VTANR5L15V584": "C",
  "VTANR5L15V585": "C",
  "VTANR5L15V59": "C",
  "VTANR5L15V599": "C",
  "VTANR5L15V60": "C",
  "VTANR5L15V600": "C",
  "VTANR5L15V601": "C",
  "VTANR5L15V602": "C",
  "VTANR5L15V603": "C",
  "VTANR5L15V604": "C",
  "VTANR5L15V605": "C",
  "VTANR5L15V606": "C",
  "VTANR5L15V607": "C",
  "VTANR5L15V608": "C",
  "VTANR5L15V609": "C",
  "VTANR5L15V62": "C",
  "VTANR5L15V63": "C",
  "VTANR5L15V64": "P",
  "VTANR5L15V65": "C",
  "VTANR5L15V66": "C",
  "VTANR5L15V68": "C",
  "VTANR5L15V700": "C",
  "VTANR5L15V701": "C",
  "VTANR5L15V702": "C",
  "VTANR5L15V703": "P",
  "VTANR5L15V704": "C",
  "VTANR5L15V705": "C",
  "VTANR5L15V706": "C",
  "VTANR5L15V707": "C",
  "VTANR5L15V708": "C",
  "VTANR5L15V709": "C",
  "VTANR5L15V710": "C",
  "VTANR5L15V711": "P",
  "VTANR5L15V712": "A",
  "VTANR5L15V713": "P",
  "VTANR5L15V718": "C",
  "VTANR5L15V729": "P",
  "VTANR5L15V732": "C",
  "VTANR5L15V733": "C",
  "VTANR5L15V762": "C",
  "VTANR5L15V817": "C",
  "VTANR5L15V818": "C",
  "VTANR5L15V819": "C",
  "VTANR5L15V926": "C",
  "VTANR5L15V927": "C",
  "VTANR5L15V928": "P",
  "VTANR5L15V941": "C",
  "VTANR5L15V942": "P",
  "VTANR5L15V945": "P",
  "VTANR5L15V946": "C",
  "VTANR5L15V947": "C",
  "VTANR5L15V974": "P",
  "VTANR5L15V993": "P",
  "VTANR5L15V994": "P",
  "VTANR5L15V995": "P"
 },
 "twitter": {
  "id": "554262922",
  "name": "Christophe Arend",
  "public_metrics": {
   "followers_count": 4705,
   "following_count": 1574,
   "listed_count": 117,
   "tweet_count": 6483
  },
  "username": "christophearend"
 },
 "twitter_username": {
  "status": "found",
  "value": "christophearend"
 },
 "uid": "PA720310"
}