{
 "an_data_depute": {},
 "an_www_depute": {
  "groupe": "Démocrate (MoDem et Indépendants)",
  "imgurl": "https://www2.assemblee-nationale.fr/static/tribun/16/photos/795100.jpg",
  "nosiege": "307"
 },
 "an_www_pic": {},
 "an_www_social": {},
 "lcdg": {
  "siege": {
   "curAngleIndex": 33,
   "curRadiusIndex": 10,
   "id": "ai33ri10",
   "no": 307,
   "polar": {
    "angle": 1.279908118129175,
    "radius": 0.9375
   },
   "pos": {
    "x": 0.26887803066664717,
    "y": -0.8982927335269555
   }
  }
 },
 "nd_twitter": {
  "twitter": "EMericmartineau",
  "url_an": "https://www2.assemblee-nationale.fr/deputes/fiche/OMC_PA795100"
 },
 "official_link": "https://www2.assemblee-nationale.fr/deputes/fiche/OMC_PA795100",
 "uid": "PA795100"
}